{
  "generatedAt": "2026-07-06T11:58:40.185Z",
  "stale": false,
  "sourceStatus": {
    "dexscreener": {
      "status": "ok",
      "observedAt": "2026-07-06T11:58:40.185Z"
    },
    "defillama": {
      "status": "ok",
      "observedAt": "2026-07-06T11:58:40.185Z"
    },
    "rpc": {
      "status": "ok",
      "observedAt": "2026-07-06T11:58:40.185Z"
    }
  },
  "chainHeads": {
    "ethereum": {
      "height": 25473345,
      "observedAt": "2026-07-06T11:58:40.502Z",
      "status": "ok"
    },
    "bsc": {
      "height": 108400605,
      "observedAt": "2026-07-06T11:58:40.509Z",
      "status": "ok"
    },
    "solana": {
      "height": 431158705,
      "observedAt": "2026-07-06T11:58:40.588Z",
      "status": "ok"
    }
  },
  "marketIndex": 68,
  "signalCount": 100,
  "disclaimer": "Research data only. AlphaOS does not provide financial advice.",
  "opportunities": [
    {
      "id": "protocol:3871",
      "kind": "protocol",
      "name": "Wildcat Protocol",
      "type": "defi",
      "chain": "Ethereum",
      "score": 89,
      "risk": {
        "level": "low",
        "reasons": [
          "未发现高优先级风险信号"
        ]
      },
      "summary": "Wildcat Protocol is a growing DeFi protocol with verifiable TVL and yield evidence.",
      "evidence": [
        "$8,883,141.36 TVL",
        "75.94% TVL change over 7 days"
      ],
      "sourceUrl": "https://defillama.com/protocol/wildcat-protocol",
      "observedAt": "2026-07-06T11:58:40.185Z"
    },
    {
      "id": "protocol:7954",
      "kind": "protocol",
      "name": "Gami Labs",
      "type": "defi",
      "chain": "Ethereum",
      "score": 86,
      "risk": {
        "level": "low",
        "reasons": [
          "未发现高优先级风险信号"
        ]
      },
      "summary": "Gami Labs is a growing DeFi protocol with verifiable TVL and yield evidence.",
      "evidence": [
        "$48,813,020.29 TVL",
        "23.09% TVL change over 7 days"
      ],
      "sourceUrl": "https://defillama.com/protocol/gami-labs",
      "observedAt": "2026-07-06T11:58:40.185Z"
    },
    {
      "id": "protocol:2776",
      "kind": "protocol",
      "name": "SushiSwap V3",
      "type": "defi",
      "chain": "Ethereum",
      "score": 82,
      "risk": {
        "level": "low",
        "reasons": [
          "未发现高优先级风险信号"
        ]
      },
      "summary": "SushiSwap V3 is a growing DeFi protocol with verifiable TVL and yield evidence.",
      "evidence": [
        "$37,805,360.09 TVL",
        "8.21% TVL change over 7 days"
      ],
      "sourceUrl": "https://defillama.com/protocol/sushiswap-v3",
      "observedAt": "2026-07-06T11:58:40.185Z"
    },
    {
      "id": "protocol:5145",
      "kind": "protocol",
      "name": "Fusion by IPOR",
      "type": "defi",
      "chain": "Ethereum",
      "score": 82,
      "risk": {
        "level": "low",
        "reasons": [
          "未发现高优先级风险信号"
        ]
      },
      "summary": "Fusion by IPOR is a growing DeFi protocol with verifiable TVL and yield evidence.",
      "evidence": [
        "$35,542,734.63 TVL",
        "13.81% TVL change over 7 days"
      ],
      "sourceUrl": "https://defillama.com/protocol/fusion-by-ipor",
      "observedAt": "2026-07-06T11:58:40.185Z"
    },
    {
      "id": "protocol:119",
      "kind": "protocol",
      "name": "SushiSwap",
      "type": "defi",
      "chain": "Ethereum",
      "score": 81,
      "risk": {
        "level": "low",
        "reasons": [
          "未发现高优先级风险信号"
        ]
      },
      "summary": "SushiSwap is a growing DeFi protocol with verifiable TVL and yield evidence.",
      "evidence": [
        "$32,877,521.26 TVL",
        "6.96% TVL change over 7 days"
      ],
      "sourceUrl": "https://defillama.com/protocol/sushiswap",
      "observedAt": "2026-07-06T11:58:40.185Z"
    },
    {
      "id": "protocol:4663",
      "kind": "protocol",
      "name": "Native Credit Pool",
      "type": "defi",
      "chain": "Ethereum",
      "score": 81,
      "risk": {
        "level": "low",
        "reasons": [
          "未发现高优先级风险信号"
        ]
      },
      "summary": "Native Credit Pool is a growing DeFi protocol with verifiable TVL and yield evidence.",
      "evidence": [
        "$33,898,767.64 TVL",
        "6.1% TVL change over 7 days"
      ],
      "sourceUrl": "https://defillama.com/protocol/native-credit-pool",
      "observedAt": "2026-07-06T11:58:40.185Z"
    },
    {
      "id": "protocol:1108",
      "kind": "protocol",
      "name": "Gearbox",
      "type": "defi",
      "chain": "Ethereum",
      "score": 80,
      "risk": {
        "level": "low",
        "reasons": [
          "未发现高优先级风险信号"
        ]
      },
      "summary": "Gearbox is a growing DeFi protocol with verifiable TVL and yield evidence.",
      "evidence": [
        "$18,097,846.64 TVL",
        "9.04% TVL change over 7 days"
      ],
      "sourceUrl": "https://defillama.com/protocol/gearbox",
      "observedAt": "2026-07-06T11:58:40.185Z"
    },
    {
      "id": "protocol:220",
      "kind": "protocol",
      "name": "Vesper",
      "type": "defi",
      "chain": "Ethereum",
      "score": 80,
      "risk": {
        "level": "low",
        "reasons": [
          "未发现高优先级风险信号"
        ]
      },
      "summary": "Vesper is a growing DeFi protocol with verifiable TVL and yield evidence.",
      "evidence": [
        "$43,002,610.67 TVL",
        "5.07% TVL change over 7 days"
      ],
      "sourceUrl": "https://defillama.com/protocol/vesper",
      "observedAt": "2026-07-06T11:58:40.185Z"
    },
    {
      "id": "protocol:278",
      "kind": "protocol",
      "name": "Ankr",
      "type": "defi",
      "chain": "Ethereum",
      "score": 80,
      "risk": {
        "level": "low",
        "reasons": [
          "未发现高优先级风险信号"
        ]
      },
      "summary": "Ankr is a growing DeFi protocol with verifiable TVL and yield evidence.",
      "evidence": [
        "$19,285,422.73 TVL",
        "8.63% TVL change over 7 days"
      ],
      "sourceUrl": "https://defillama.com/protocol/ankr",
      "observedAt": "2026-07-06T11:58:40.185Z"
    },
    {
      "id": "protocol:2993",
      "kind": "protocol",
      "name": "NodeDAO",
      "type": "defi",
      "chain": "Ethereum",
      "score": 80,
      "risk": {
        "level": "low",
        "reasons": [
          "未发现高优先级风险信号"
        ]
      },
      "summary": "NodeDAO is a growing DeFi protocol with verifiable TVL and yield evidence.",
      "evidence": [
        "$25,108,814.64 TVL",
        "12.29% TVL change over 7 days"
      ],
      "sourceUrl": "https://defillama.com/protocol/nodedao",
      "observedAt": "2026-07-06T11:58:40.185Z"
    },
    {
      "id": "protocol:5915",
      "kind": "protocol",
      "name": "YO Protocol",
      "type": "defi",
      "chain": "Ethereum",
      "score": 80,
      "risk": {
        "level": "low",
        "reasons": [
          "未发现高优先级风险信号"
        ]
      },
      "summary": "YO Protocol is a growing DeFi protocol with verifiable TVL and yield evidence.",
      "evidence": [
        "$35,929,073 TVL",
        "2.75% TVL change over 7 days"
      ],
      "sourceUrl": "https://defillama.com/protocol/yo-protocol",
      "observedAt": "2026-07-06T11:58:40.185Z"
    },
    {
      "id": "protocol:626",
      "kind": "protocol",
      "name": "Reserve Protocol",
      "type": "defi",
      "chain": "Ethereum",
      "score": 80,
      "risk": {
        "level": "low",
        "reasons": [
          "未发现高优先级风险信号"
        ]
      },
      "summary": "Reserve Protocol is a growing DeFi protocol with verifiable TVL and yield evidence.",
      "evidence": [
        "$38,985,246.2 TVL",
        "0.93% TVL change over 7 days"
      ],
      "sourceUrl": "https://defillama.com/protocol/reserve-protocol",
      "observedAt": "2026-07-06T11:58:40.185Z"
    },
    {
      "id": "protocol:3405",
      "kind": "protocol",
      "name": "Meta Pool ETH",
      "type": "defi",
      "chain": "Ethereum",
      "score": 79,
      "risk": {
        "level": "low",
        "reasons": [
          "未发现高优先级风险信号"
        ]
      },
      "summary": "Meta Pool ETH is a growing DeFi protocol with verifiable TVL and yield evidence.",
      "evidence": [
        "$18,571,530.54 TVL",
        "12.29% TVL change over 7 days"
      ],
      "sourceUrl": "https://defillama.com/protocol/meta-pool-eth",
      "observedAt": "2026-07-06T11:58:40.185Z"
    },
    {
      "id": "protocol:4606",
      "kind": "protocol",
      "name": "YieldNest",
      "type": "defi",
      "chain": "Ethereum",
      "score": 79,
      "risk": {
        "level": "low",
        "reasons": [
          "未发现高优先级风险信号"
        ]
      },
      "summary": "YieldNest is a growing DeFi protocol with verifiable TVL and yield evidence.",
      "evidence": [
        "$19,973,441.66 TVL",
        "6.04% TVL change over 7 days"
      ],
      "sourceUrl": "https://defillama.com/protocol/yieldnest",
      "observedAt": "2026-07-06T11:58:40.185Z"
    },
    {
      "id": "protocol:1995",
      "kind": "protocol",
      "name": "Bancor V3",
      "type": "defi",
      "chain": "Ethereum",
      "score": 78,
      "risk": {
        "level": "low",
        "reasons": [
          "未发现高优先级风险信号"
        ]
      },
      "summary": "Bancor V3 is a growing DeFi protocol with verifiable TVL and yield evidence.",
      "evidence": [
        "$16,737,594.27 TVL",
        "9.42% TVL change over 7 days"
      ],
      "sourceUrl": "https://defillama.com/protocol/bancor-v3",
      "observedAt": "2026-07-06T11:58:40.185Z"
    },
    {
      "id": "protocol:2076",
      "kind": "protocol",
      "name": "Fraxlend",
      "type": "defi",
      "chain": "Ethereum",
      "score": 78,
      "risk": {
        "level": "low",
        "reasons": [
          "未发现高优先级风险信号"
        ]
      },
      "summary": "Fraxlend is a growing DeFi protocol with verifiable TVL and yield evidence.",
      "evidence": [
        "$20,526,651.5 TVL",
        "7.38% TVL change over 7 days"
      ],
      "sourceUrl": "https://defillama.com/protocol/fraxlend",
      "observedAt": "2026-07-06T11:58:40.185Z"
    },
    {
      "id": "protocol:2537",
      "kind": "protocol",
      "name": "Flux Finance",
      "type": "defi",
      "chain": "Ethereum",
      "score": 78,
      "risk": {
        "level": "low",
        "reasons": [
          "未发现高优先级风险信号"
        ]
      },
      "summary": "Flux Finance is a growing DeFi protocol with verifiable TVL and yield evidence.",
      "evidence": [
        "$44,210,226.39 TVL",
        "0.02% TVL change over 7 days"
      ],
      "sourceUrl": "https://defillama.com/protocol/flux-finance",
      "observedAt": "2026-07-06T11:58:40.185Z"
    },
    {
      "id": "protocol:5611",
      "kind": "protocol",
      "name": "Silo V2",
      "type": "defi",
      "chain": "Ethereum",
      "score": 78,
      "risk": {
        "level": "low",
        "reasons": [
          "未发现高优先级风险信号"
        ]
      },
      "summary": "Silo V2 is a growing DeFi protocol with verifiable TVL and yield evidence.",
      "evidence": [
        "$11,725,614.3 TVL",
        "30.96% TVL change over 7 days"
      ],
      "sourceUrl": "https://defillama.com/protocol/silo-v2",
      "observedAt": "2026-07-06T11:58:40.185Z"
    },
    {
      "id": "protocol:6024",
      "kind": "protocol",
      "name": "Aegis YUSD",
      "type": "defi",
      "chain": "Ethereum",
      "score": 78,
      "risk": {
        "level": "low",
        "reasons": [
          "未发现高优先级风险信号"
        ]
      },
      "summary": "Aegis YUSD is a growing DeFi protocol with verifiable TVL and yield evidence.",
      "evidence": [
        "$35,782,201.32 TVL",
        "0.08% TVL change over 7 days"
      ],
      "sourceUrl": "https://defillama.com/protocol/aegis-yusd",
      "observedAt": "2026-07-06T11:58:40.185Z"
    },
    {
      "id": "protocol:1207",
      "kind": "protocol",
      "name": "Across",
      "type": "defi",
      "chain": "Ethereum",
      "score": 77,
      "risk": {
        "level": "low",
        "reasons": [
          "未发现高优先级风险信号"
        ]
      },
      "summary": "Across is a growing DeFi protocol with verifiable TVL and yield evidence.",
      "evidence": [
        "$20,069,291.11 TVL",
        "5.8% TVL change over 7 days"
      ],
      "sourceUrl": "https://defillama.com/protocol/across",
      "observedAt": "2026-07-06T11:58:40.185Z"
    },
    {
      "id": "protocol:438",
      "kind": "protocol",
      "name": "AUTOfinance",
      "type": "defi",
      "chain": "Ethereum",
      "score": 77,
      "risk": {
        "level": "low",
        "reasons": [
          "未发现高优先级风险信号"
        ]
      },
      "summary": "AUTOfinance is a growing DeFi protocol with verifiable TVL and yield evidence.",
      "evidence": [
        "$30,655,516.41 TVL",
        "1.02% TVL change over 7 days"
      ],
      "sourceUrl": "https://defillama.com/protocol/autofinance",
      "observedAt": "2026-07-06T11:58:40.185Z"
    },
    {
      "id": "protocol:5963",
      "kind": "protocol",
      "name": "Resupply",
      "type": "defi",
      "chain": "Ethereum",
      "score": 77,
      "risk": {
        "level": "low",
        "reasons": [
          "未发现高优先级风险信号"
        ]
      },
      "summary": "Resupply is a growing DeFi protocol with verifiable TVL and yield evidence.",
      "evidence": [
        "$35,013,036.44 TVL",
        "0.14% TVL change over 7 days"
      ],
      "sourceUrl": "https://defillama.com/protocol/resupply",
      "observedAt": "2026-07-06T11:58:40.185Z"
    },
    {
      "id": "protocol:2433",
      "kind": "protocol",
      "name": "Inverse Finance FiRM",
      "type": "defi",
      "chain": "Ethereum",
      "score": 76,
      "risk": {
        "level": "low",
        "reasons": [
          "未发现高优先级风险信号"
        ]
      },
      "summary": "Inverse Finance FiRM is a growing DeFi protocol with verifiable TVL and yield evidence.",
      "evidence": [
        "$18,696,131.95 TVL",
        "3.4% TVL change over 7 days"
      ],
      "sourceUrl": "https://defillama.com/protocol/inverse-finance-firm",
      "observedAt": "2026-07-06T11:58:40.185Z"
    },
    {
      "id": "protocol:6659",
      "kind": "protocol",
      "name": "3Jane Lending",
      "type": "defi",
      "chain": "Ethereum",
      "score": 76,
      "risk": {
        "level": "low",
        "reasons": [
          "未发现高优先级风险信号"
        ]
      },
      "summary": "3Jane Lending is a growing DeFi protocol with verifiable TVL and yield evidence.",
      "evidence": [
        "$21,060,765.13 TVL",
        "3.13% TVL change over 7 days"
      ],
      "sourceUrl": "https://defillama.com/protocol/3jane-lending",
      "observedAt": "2026-07-06T11:58:40.185Z"
    },
    {
      "id": "protocol:1594",
      "kind": "protocol",
      "name": "Symbiosis",
      "type": "defi",
      "chain": "Ethereum",
      "score": 75,
      "risk": {
        "level": "low",
        "reasons": [
          "未发现高优先级风险信号"
        ]
      },
      "summary": "Symbiosis is a growing DeFi protocol with verifiable TVL and yield evidence.",
      "evidence": [
        "$9,106,816.77 TVL",
        "1.45% TVL change over 7 days"
      ],
      "sourceUrl": "https://defillama.com/protocol/symbiosis",
      "observedAt": "2026-07-06T11:58:40.185Z"
    },
    {
      "id": "protocol:2901",
      "kind": "protocol",
      "name": "Swell Liquid Staking",
      "type": "defi",
      "chain": "Ethereum",
      "score": 74,
      "risk": {
        "level": "low",
        "reasons": [
          "未发现高优先级风险信号"
        ]
      },
      "summary": "Swell Liquid Staking is a growing DeFi protocol with verifiable TVL and yield evidence.",
      "evidence": [
        "$24,254,655.36 TVL",
        "11.15% TVL change over 7 days"
      ],
      "sourceUrl": "https://defillama.com/protocol/swell-liquid-staking",
      "observedAt": "2026-07-06T11:58:40.185Z"
    },
    {
      "id": "protocol:4078",
      "kind": "protocol",
      "name": "Swell Liquid Restaking",
      "type": "defi",
      "chain": "Ethereum",
      "score": 74,
      "risk": {
        "level": "low",
        "reasons": [
          "未发现高优先级风险信号"
        ]
      },
      "summary": "Swell Liquid Restaking is a growing DeFi protocol with verifiable TVL and yield evidence.",
      "evidence": [
        "$22,217,008.31 TVL",
        "11.78% TVL change over 7 days"
      ],
      "sourceUrl": "https://defillama.com/protocol/swell-liquid-restaking",
      "observedAt": "2026-07-06T11:58:40.185Z"
    },
    {
      "id": "protocol:4088",
      "kind": "protocol",
      "name": "Puffer Stake",
      "type": "defi",
      "chain": "Ethereum",
      "score": 74,
      "risk": {
        "level": "low",
        "reasons": [
          "未发现高优先级风险信号"
        ]
      },
      "summary": "Puffer Stake is a growing DeFi protocol with verifiable TVL and yield evidence.",
      "evidence": [
        "$43,558,217.91 TVL",
        "3.35% TVL change over 7 days"
      ],
      "sourceUrl": "https://defillama.com/protocol/puffer-stake",
      "observedAt": "2026-07-06T11:58:40.185Z"
    },
    {
      "id": "protocol:5294",
      "kind": "protocol",
      "name": "Kyros",
      "type": "defi",
      "chain": "Solana",
      "score": 74,
      "risk": {
        "level": "low",
        "reasons": [
          "未发现高优先级风险信号"
        ]
      },
      "summary": "Kyros is a growing DeFi protocol with verifiable TVL and yield evidence.",
      "evidence": [
        "$9,394,871.81 TVL",
        "5.51% TVL change over 7 days"
      ],
      "sourceUrl": "https://defillama.com/protocol/kyros",
      "observedAt": "2026-07-06T11:58:40.185Z"
    },
    {
      "id": "protocol:2454",
      "kind": "protocol",
      "name": "GETH",
      "type": "defi",
      "chain": "Ethereum",
      "score": 73,
      "risk": {
        "level": "low",
        "reasons": [
          "未发现高优先级风险信号"
        ]
      },
      "summary": "GETH is a growing DeFi protocol with verifiable TVL and yield evidence.",
      "evidence": [
        "$13,548,434.35 TVL",
        "12.32% TVL change over 7 days"
      ],
      "sourceUrl": "https://defillama.com/protocol/geth",
      "observedAt": "2026-07-06T11:58:40.185Z"
    },
    {
      "id": "protocol:2611",
      "kind": "protocol",
      "name": "Balancer V2",
      "type": "defi",
      "chain": "Ethereum",
      "score": 73,
      "risk": {
        "level": "low",
        "reasons": [
          "未发现高优先级风险信号"
        ]
      },
      "summary": "Balancer V2 is a growing DeFi protocol with verifiable TVL and yield evidence.",
      "evidence": [
        "$28,096,426.84 TVL",
        "4.83% TVL change over 7 days"
      ],
      "sourceUrl": "https://defillama.com/protocol/balancer-v2",
      "observedAt": "2026-07-06T11:58:40.185Z"
    },
    {
      "id": "protocol:2832",
      "kind": "protocol",
      "name": "Bedrock uniETH",
      "type": "defi",
      "chain": "Ethereum",
      "score": 73,
      "risk": {
        "level": "low",
        "reasons": [
          "未发现高优先级风险信号"
        ]
      },
      "summary": "Bedrock uniETH is a growing DeFi protocol with verifiable TVL and yield evidence.",
      "evidence": [
        "$18,354,272.83 TVL",
        "11.5% TVL change over 7 days"
      ],
      "sourceUrl": "https://defillama.com/protocol/bedrock-unieth",
      "observedAt": "2026-07-06T11:58:40.185Z"
    },
    {
      "id": "protocol:6648",
      "kind": "protocol",
      "name": "Hylo LSTs",
      "type": "defi",
      "chain": "Solana",
      "score": 73,
      "risk": {
        "level": "low",
        "reasons": [
          "未发现高优先级风险信号"
        ]
      },
      "summary": "Hylo LSTs is a growing DeFi protocol with verifiable TVL and yield evidence.",
      "evidence": [
        "$15,826,425.12 TVL",
        "12.01% TVL change over 7 days"
      ],
      "sourceUrl": "https://defillama.com/protocol/hylo-lsts",
      "observedAt": "2026-07-06T11:58:40.185Z"
    },
    {
      "id": "protocol:6905",
      "kind": "protocol",
      "name": "Avant avETH",
      "type": "defi",
      "chain": "Ethereum",
      "score": 73,
      "risk": {
        "level": "low",
        "reasons": [
          "未发现高优先级风险信号"
        ]
      },
      "summary": "Avant avETH is a growing DeFi protocol with verifiable TVL and yield evidence.",
      "evidence": [
        "$16,109,790.64 TVL",
        "11.91% TVL change over 7 days"
      ],
      "sourceUrl": "https://defillama.com/protocol/avant-aveth",
      "observedAt": "2026-07-06T11:58:40.185Z"
    },
    {
      "id": "protocol:3499",
      "kind": "protocol",
      "name": "Ekubo",
      "type": "defi",
      "chain": "Ethereum",
      "score": 72,
      "risk": {
        "level": "high",
        "reasons": [
          "存在高优先级风险信号"
        ]
      },
      "summary": "Ekubo is a growing DeFi protocol with verifiable TVL and yield evidence.",
      "evidence": [
        "$22,247,471.51 TVL",
        "8.28% TVL change over 7 days"
      ],
      "sourceUrl": "https://defillama.com/protocol/ekubo",
      "observedAt": "2026-07-06T11:58:40.185Z"
    },
    {
      "id": "protocol:2950",
      "kind": "protocol",
      "name": "Origin Ether",
      "type": "defi",
      "chain": "Ethereum",
      "score": 71,
      "risk": {
        "level": "low",
        "reasons": [
          "未发现高优先级风险信号"
        ]
      },
      "summary": "Origin Ether is a growing DeFi protocol with verifiable TVL and yield evidence.",
      "evidence": [
        "$31,338,485.92 TVL",
        "6.44% TVL change over 7 days"
      ],
      "sourceUrl": "https://defillama.com/protocol/origin-ether",
      "observedAt": "2026-07-06T11:58:40.185Z"
    },
    {
      "id": "protocol:4994",
      "kind": "protocol",
      "name": "Bonk Staked SOL",
      "type": "defi",
      "chain": "Solana",
      "score": 71,
      "risk": {
        "level": "low",
        "reasons": [
          "未发现高优先级风险信号"
        ]
      },
      "summary": "Bonk Staked SOL is a growing DeFi protocol with verifiable TVL and yield evidence.",
      "evidence": [
        "$11,108,567.84 TVL",
        "10.83% TVL change over 7 days"
      ],
      "sourceUrl": "https://defillama.com/protocol/bonk-staked-sol",
      "observedAt": "2026-07-06T11:58:40.185Z"
    },
    {
      "id": "protocol:112",
      "kind": "protocol",
      "name": "Harvest Finance",
      "type": "defi",
      "chain": "Ethereum",
      "score": 70,
      "risk": {
        "level": "low",
        "reasons": [
          "未发现高优先级风险信号"
        ]
      },
      "summary": "Harvest Finance is a growing DeFi protocol with verifiable TVL and yield evidence.",
      "evidence": [
        "$11,666,765.79 TVL",
        "4.75% TVL change over 7 days"
      ],
      "sourceUrl": "https://defillama.com/protocol/harvest-finance",
      "observedAt": "2026-07-06T11:58:40.185Z"
    },
    {
      "id": "protocol:3570",
      "kind": "protocol",
      "name": "marginfi LST",
      "type": "defi",
      "chain": "Solana",
      "score": 70,
      "risk": {
        "level": "low",
        "reasons": [
          "未发现高优先级风险信号"
        ]
      },
      "summary": "marginfi LST is a growing DeFi protocol with verifiable TVL and yield evidence.",
      "evidence": [
        "$7,551,013.69 TVL",
        "10.94% TVL change over 7 days"
      ],
      "sourceUrl": "https://defillama.com/protocol/marginfi-lst",
      "observedAt": "2026-07-06T11:58:40.185Z"
    },
    {
      "id": "protocol:4692",
      "kind": "protocol",
      "name": "Taiko Bridge",
      "type": "defi",
      "chain": "Ethereum",
      "score": 70,
      "risk": {
        "level": "medium",
        "reasons": [
          "存在需要进一步核验的风险信号"
        ]
      },
      "summary": "Taiko Bridge is a growing DeFi protocol with verifiable TVL and yield evidence.",
      "evidence": [
        "$12,997,324.32 TVL",
        "51.14% TVL change over 7 days"
      ],
      "sourceUrl": "https://defillama.com/protocol/taiko-bridge",
      "observedAt": "2026-07-06T11:58:40.185Z"
    },
    {
      "id": "protocol:6804",
      "kind": "protocol",
      "name": "alphagrowth",
      "type": "defi",
      "chain": "Ethereum",
      "score": 70,
      "risk": {
        "level": "medium",
        "reasons": [
          "存在需要进一步核验的风险信号"
        ]
      },
      "summary": "alphagrowth is a growing DeFi protocol with verifiable TVL and yield evidence.",
      "evidence": [
        "$12,977,398.36 TVL",
        "80.8% TVL change over 7 days"
      ],
      "sourceUrl": "https://defillama.com/protocol/alphagrowth",
      "observedAt": "2026-07-06T11:58:40.185Z"
    },
    {
      "id": "protocol:1738",
      "kind": "protocol",
      "name": "Bifrost Liquid Staking",
      "type": "defi",
      "chain": "Ethereum",
      "score": 69,
      "risk": {
        "level": "low",
        "reasons": [
          "未发现高优先级风险信号"
        ]
      },
      "summary": "Bifrost Liquid Staking is a growing DeFi protocol with verifiable TVL and yield evidence.",
      "evidence": [
        "$14,677,385.62 TVL",
        "1.7% TVL change over 7 days"
      ],
      "sourceUrl": "https://defillama.com/protocol/bifrost-liquid-staking",
      "observedAt": "2026-07-06T11:58:40.185Z"
    },
    {
      "id": "protocol:3912",
      "kind": "protocol",
      "name": "Dinero (pxETH)",
      "type": "defi",
      "chain": "Ethereum",
      "score": 68,
      "risk": {
        "level": "medium",
        "reasons": [
          "存在需要进一步核验的风险信号"
        ]
      },
      "summary": "Dinero (pxETH) is a growing DeFi protocol with verifiable TVL and yield evidence.",
      "evidence": [
        "$4,100,248.78 TVL",
        "11.93% TVL change over 7 days"
      ],
      "sourceUrl": "https://defillama.com/protocol/dinero-(pxeth)",
      "observedAt": "2026-07-06T11:58:40.185Z"
    },
    {
      "id": "protocol:6085",
      "kind": "protocol",
      "name": "Save SOL",
      "type": "defi",
      "chain": "Solana",
      "score": 68,
      "risk": {
        "level": "medium",
        "reasons": [
          "存在需要进一步核验的风险信号"
        ]
      },
      "summary": "Save SOL is a growing DeFi protocol with verifiable TVL and yield evidence.",
      "evidence": [
        "$4,277,647.36 TVL",
        "10.51% TVL change over 7 days"
      ],
      "sourceUrl": "https://defillama.com/protocol/save-sol",
      "observedAt": "2026-07-06T11:58:40.185Z"
    },
    {
      "id": "protocol:7329",
      "kind": "protocol",
      "name": "Fira",
      "type": "defi",
      "chain": "Ethereum",
      "score": 68,
      "risk": {
        "level": "low",
        "reasons": [
          "未发现高优先级风险信号"
        ]
      },
      "summary": "Fira is a growing DeFi protocol with verifiable TVL and yield evidence.",
      "evidence": [
        "$6,087,817.6 TVL",
        "7.05% TVL change over 7 days"
      ],
      "sourceUrl": "https://defillama.com/protocol/fira",
      "observedAt": "2026-07-06T11:58:40.185Z"
    },
    {
      "id": "protocol:1700",
      "kind": "protocol",
      "name": "Wombat Exchange",
      "type": "defi",
      "chain": "BNB Chain",
      "score": 67,
      "risk": {
        "level": "medium",
        "reasons": [
          "存在需要进一步核验的风险信号"
        ]
      },
      "summary": "Wombat Exchange is a growing DeFi protocol with verifiable TVL and yield evidence.",
      "evidence": [
        "$1,423,584.63 TVL",
        "2.37% TVL change over 7 days"
      ],
      "sourceUrl": "https://defillama.com/protocol/wombat-exchange",
      "observedAt": "2026-07-06T11:58:40.185Z"
    },
    {
      "id": "protocol:334",
      "kind": "protocol",
      "name": "MDEX",
      "type": "defi",
      "chain": "BNB Chain",
      "score": 67,
      "risk": {
        "level": "medium",
        "reasons": [
          "存在需要进一步核验的风险信号"
        ]
      },
      "summary": "MDEX is a growing DeFi protocol with verifiable TVL and yield evidence.",
      "evidence": [
        "$1,282,651.66 TVL",
        "2.75% TVL change over 7 days"
      ],
      "sourceUrl": "https://defillama.com/protocol/mdex",
      "observedAt": "2026-07-06T11:58:40.185Z"
    },
    {
      "id": "protocol:4223",
      "kind": "protocol",
      "name": "Ring Few",
      "type": "defi",
      "chain": "Ethereum",
      "score": 67,
      "risk": {
        "level": "medium",
        "reasons": [
          "存在需要进一步核验的风险信号"
        ]
      },
      "summary": "Ring Few is a growing DeFi protocol with verifiable TVL and yield evidence.",
      "evidence": [
        "$30,092,198.93 TVL",
        "27% TVL change over 7 days"
      ],
      "sourceUrl": "https://defillama.com/protocol/ring-few",
      "observedAt": "2026-07-06T11:58:40.185Z"
    },
    {
      "id": "protocol:6460",
      "kind": "protocol",
      "name": "Laine SOL",
      "type": "defi",
      "chain": "Solana",
      "score": 67,
      "risk": {
        "level": "medium",
        "reasons": [
          "存在需要进一步核验的风险信号"
        ]
      },
      "summary": "Laine SOL is a growing DeFi protocol with verifiable TVL and yield evidence.",
      "evidence": [
        "$2,820,750.32 TVL",
        "10.63% TVL change over 7 days"
      ],
      "sourceUrl": "https://defillama.com/protocol/laine-sol",
      "observedAt": "2026-07-06T11:58:40.185Z"
    },
    {
      "id": "protocol:6471",
      "kind": "protocol",
      "name": "Stronghold Staked SOL",
      "type": "defi",
      "chain": "Solana",
      "score": 67,
      "risk": {
        "level": "medium",
        "reasons": [
          "存在需要进一步核验的风险信号"
        ]
      },
      "summary": "Stronghold Staked SOL is a growing DeFi protocol with verifiable TVL and yield evidence.",
      "evidence": [
        "$3,772,665.69 TVL",
        "10.26% TVL change over 7 days"
      ],
      "sourceUrl": "https://defillama.com/protocol/stronghold-staked-sol",
      "observedAt": "2026-07-06T11:58:40.185Z"
    },
    {
      "id": "protocol:6966",
      "kind": "protocol",
      "name": "TurboFlow Perps",
      "type": "defi",
      "chain": "BNB Chain",
      "score": 67,
      "risk": {
        "level": "medium",
        "reasons": [
          "存在需要进一步核验的风险信号"
        ]
      },
      "summary": "TurboFlow Perps is a growing DeFi protocol with verifiable TVL and yield evidence.",
      "evidence": [
        "$3,754,861.6 TVL",
        "73.98% TVL change over 7 days"
      ],
      "sourceUrl": "https://defillama.com/protocol/turboflow-perps",
      "observedAt": "2026-07-06T11:58:40.185Z"
    },
    {
      "id": "protocol:7631",
      "kind": "protocol",
      "name": "Spectra MetaVaults",
      "type": "defi",
      "chain": "Ethereum",
      "score": 67,
      "risk": {
        "level": "high",
        "reasons": [
          "存在高优先级风险信号"
        ]
      },
      "summary": "Spectra MetaVaults is a growing DeFi protocol with verifiable TVL and yield evidence.",
      "evidence": [
        "$11,818,436.63 TVL",
        "237.49% TVL change over 7 days"
      ],
      "sourceUrl": "https://defillama.com/protocol/spectra-metavaults",
      "observedAt": "2026-07-06T11:58:40.185Z"
    },
    {
      "id": "protocol:3171",
      "kind": "protocol",
      "name": "Kinza Finance",
      "type": "defi",
      "chain": "BNB Chain",
      "score": 66,
      "risk": {
        "level": "medium",
        "reasons": [
          "存在需要进一步核验的风险信号"
        ]
      },
      "summary": "Kinza Finance is a growing DeFi protocol with verifiable TVL and yield evidence.",
      "evidence": [
        "$3,311,568.5 TVL",
        "1.86% TVL change over 7 days"
      ],
      "sourceUrl": "https://defillama.com/protocol/kinza-finance",
      "observedAt": "2026-07-06T11:58:40.185Z"
    },
    {
      "id": "protocol:5814",
      "kind": "protocol",
      "name": "Pico Staked SOL",
      "type": "defi",
      "chain": "Solana",
      "score": 65,
      "risk": {
        "level": "medium",
        "reasons": [
          "存在需要进一步核验的风险信号"
        ]
      },
      "summary": "Pico Staked SOL is a growing DeFi protocol with verifiable TVL and yield evidence.",
      "evidence": [
        "$1,703,879.58 TVL",
        "11.05% TVL change over 7 days"
      ],
      "sourceUrl": "https://defillama.com/protocol/pico-staked-sol",
      "observedAt": "2026-07-06T11:58:40.185Z"
    },
    {
      "id": "protocol:151",
      "kind": "protocol",
      "name": "Rhino.fi",
      "type": "defi",
      "chain": "Ethereum",
      "score": 64,
      "risk": {
        "level": "medium",
        "reasons": [
          "存在需要进一步核验的风险信号"
        ]
      },
      "summary": "Rhino.fi is a growing DeFi protocol with verifiable TVL and yield evidence.",
      "evidence": [
        "$2,505,397.5 TVL",
        "96.9% TVL change over 7 days"
      ],
      "sourceUrl": "https://defillama.com/protocol/rhino.fi",
      "observedAt": "2026-07-06T11:58:40.185Z"
    },
    {
      "id": "protocol:427",
      "kind": "protocol",
      "name": "Origin Dollar",
      "type": "defi",
      "chain": "Ethereum",
      "score": 64,
      "risk": {
        "level": "low",
        "reasons": [
          "未发现高优先级风险信号"
        ]
      },
      "summary": "Origin Dollar is a growing DeFi protocol with verifiable TVL and yield evidence.",
      "evidence": [
        "$7,450,523.49 TVL",
        "0.46% TVL change over 7 days"
      ],
      "sourceUrl": "https://defillama.com/protocol/origin-dollar",
      "observedAt": "2026-07-06T11:58:40.185Z"
    },
    {
      "id": "protocol:2867",
      "kind": "protocol",
      "name": "Ensuro",
      "type": "defi",
      "chain": "Ethereum",
      "score": 63,
      "risk": {
        "level": "medium",
        "reasons": [
          "存在需要进一步核验的风险信号"
        ]
      },
      "summary": "Ensuro is a growing DeFi protocol with verifiable TVL and yield evidence.",
      "evidence": [
        "$1,201,794.43 TVL",
        "9.19% TVL change over 7 days"
      ],
      "sourceUrl": "https://defillama.com/protocol/ensuro",
      "observedAt": "2026-07-06T11:58:40.185Z"
    },
    {
      "id": "protocol:6238",
      "kind": "protocol",
      "name": "SMARDEX USDN",
      "type": "defi",
      "chain": "Ethereum",
      "score": 63,
      "risk": {
        "level": "medium",
        "reasons": [
          "存在需要进一步核验的风险信号"
        ]
      },
      "summary": "SMARDEX USDN is a growing DeFi protocol with verifiable TVL and yield evidence.",
      "evidence": [
        "$1,129,631.33 TVL",
        "9.47% TVL change over 7 days"
      ],
      "sourceUrl": "https://defillama.com/protocol/smardex-usdn",
      "observedAt": "2026-07-06T11:58:40.185Z"
    },
    {
      "id": "protocol:6504",
      "kind": "protocol",
      "name": "Bracket Vaults",
      "type": "defi",
      "chain": "Ethereum",
      "score": 63,
      "risk": {
        "level": "medium",
        "reasons": [
          "存在需要进一步核验的风险信号"
        ]
      },
      "summary": "Bracket Vaults is a growing DeFi protocol with verifiable TVL and yield evidence.",
      "evidence": [
        "$2,759,522.74 TVL",
        "0.41% TVL change over 7 days"
      ],
      "sourceUrl": "https://defillama.com/protocol/bracket-vaults",
      "observedAt": "2026-07-06T11:58:40.185Z"
    },
    {
      "id": "protocol:7464",
      "kind": "protocol",
      "name": "Usual ETH0",
      "type": "defi",
      "chain": "Ethereum",
      "score": 63,
      "risk": {
        "level": "medium",
        "reasons": [
          "存在需要进一步核验的风险信号"
        ]
      },
      "summary": "Usual ETH0 is a growing DeFi protocol with verifiable TVL and yield evidence.",
      "evidence": [
        "$1,616,117.59 TVL",
        "12.4% TVL change over 7 days"
      ],
      "sourceUrl": "https://defillama.com/protocol/usual-eth0",
      "observedAt": "2026-07-06T11:58:40.185Z"
    },
    {
      "id": "protocol:3388",
      "kind": "protocol",
      "name": "Sanctum Reserve",
      "type": "defi",
      "chain": "Solana",
      "score": 62,
      "risk": {
        "level": "medium",
        "reasons": [
          "存在需要进一步核验的风险信号"
        ]
      },
      "summary": "Sanctum Reserve is a growing DeFi protocol with verifiable TVL and yield evidence.",
      "evidence": [
        "$49,746,857.32 TVL",
        "10.85% TVL change over 7 days"
      ],
      "sourceUrl": "https://defillama.com/protocol/sanctum-reserve",
      "observedAt": "2026-07-06T11:58:40.185Z"
    },
    {
      "id": "protocol:3786",
      "kind": "protocol",
      "name": "Scroll Bridge",
      "type": "defi",
      "chain": "Ethereum",
      "score": 62,
      "risk": {
        "level": "medium",
        "reasons": [
          "存在需要进一步核验的风险信号"
        ]
      },
      "summary": "Scroll Bridge is a growing DeFi protocol with verifiable TVL and yield evidence.",
      "evidence": [
        "$37,862,392.06 TVL",
        "15.61% TVL change over 7 days"
      ],
      "sourceUrl": "https://defillama.com/protocol/scroll-bridge",
      "observedAt": "2026-07-06T11:58:40.185Z"
    },
    {
      "id": "protocol:3944",
      "kind": "protocol",
      "name": "Allbridge Core",
      "type": "defi",
      "chain": "Ethereum",
      "score": 62,
      "risk": {
        "level": "medium",
        "reasons": [
          "存在需要进一步核验的风险信号"
        ]
      },
      "summary": "Allbridge Core is a growing DeFi protocol with verifiable TVL and yield evidence.",
      "evidence": [
        "$21,952,547.45 TVL",
        "11.44% TVL change over 7 days"
      ],
      "sourceUrl": "https://defillama.com/protocol/allbridge-core",
      "observedAt": "2026-07-06T11:58:40.185Z"
    },
    {
      "id": "protocol:4602",
      "kind": "protocol",
      "name": "vfat.io",
      "type": "defi",
      "chain": "Ethereum",
      "score": 62,
      "risk": {
        "level": "medium",
        "reasons": [
          "存在需要进一步核验的风险信号"
        ]
      },
      "summary": "vfat.io is a growing DeFi protocol with verifiable TVL and yield evidence.",
      "evidence": [
        "$30,095,940.75 TVL",
        "10.34% TVL change over 7 days"
      ],
      "sourceUrl": "https://defillama.com/protocol/vfat.io",
      "observedAt": "2026-07-06T11:58:40.185Z"
    },
    {
      "id": "protocol:6213",
      "kind": "protocol",
      "name": "Tulipa Capital",
      "type": "defi",
      "chain": "Ethereum",
      "score": 62,
      "risk": {
        "level": "medium",
        "reasons": [
          "存在需要进一步核验的风险信号"
        ]
      },
      "summary": "Tulipa Capital is a growing DeFi protocol with verifiable TVL and yield evidence.",
      "evidence": [
        "$41,890,495.47 TVL",
        "6.68% TVL change over 7 days"
      ],
      "sourceUrl": "https://defillama.com/protocol/tulipa-capital",
      "observedAt": "2026-07-06T11:58:40.185Z"
    },
    {
      "id": "protocol:6745",
      "kind": "protocol",
      "name": "Adrastea Restaking Operator",
      "type": "defi",
      "chain": "Solana",
      "score": 62,
      "risk": {
        "level": "high",
        "reasons": [
          "存在高优先级风险信号"
        ]
      },
      "summary": "Adrastea Restaking Operator is a growing DeFi protocol with verifiable TVL and yield evidence.",
      "evidence": [
        "$2,595,200.82 TVL",
        "229.46% TVL change over 7 days"
      ],
      "sourceUrl": "https://defillama.com/protocol/adrastea-restaking-operator",
      "observedAt": "2026-07-06T11:58:40.185Z"
    },
    {
      "id": "protocol:7313",
      "kind": "protocol",
      "name": "Lantern Staked SOL",
      "type": "defi",
      "chain": "Solana",
      "score": 62,
      "risk": {
        "level": "medium",
        "reasons": [
          "存在需要进一步核验的风险信号"
        ]
      },
      "summary": "Lantern Staked SOL is a growing DeFi protocol with verifiable TVL and yield evidence.",
      "evidence": [
        "$1,356,962 TVL",
        "4.03% TVL change over 7 days"
      ],
      "sourceUrl": "https://defillama.com/protocol/lantern-staked-sol",
      "observedAt": "2026-07-06T11:58:40.185Z"
    },
    {
      "id": "protocol:7414",
      "kind": "protocol",
      "name": "tramplin.io",
      "type": "defi",
      "chain": "Solana",
      "score": 62,
      "risk": {
        "level": "medium",
        "reasons": [
          "存在需要进一步核验的风险信号"
        ]
      },
      "summary": "tramplin.io is a growing DeFi protocol with verifiable TVL and yield evidence.",
      "evidence": [
        "$1,677,664.97 TVL",
        "2.87% TVL change over 7 days"
      ],
      "sourceUrl": "https://defillama.com/protocol/tramplin.io",
      "observedAt": "2026-07-06T11:58:40.185Z"
    },
    {
      "id": "protocol:1853",
      "kind": "protocol",
      "name": "Moonwell Lending",
      "type": "defi",
      "chain": "Ethereum",
      "score": 61,
      "risk": {
        "level": "medium",
        "reasons": [
          "存在需要进一步核验的风险信号"
        ]
      },
      "summary": "Moonwell Lending is a growing DeFi protocol with verifiable TVL and yield evidence.",
      "evidence": [
        "$49,975,103.13 TVL",
        "7.43% TVL change over 7 days"
      ],
      "sourceUrl": "https://defillama.com/protocol/moonwell-lending",
      "observedAt": "2026-07-06T11:58:40.185Z"
    },
    {
      "id": "protocol:3208",
      "kind": "protocol",
      "name": "UNCX Network V3",
      "type": "defi",
      "chain": "Ethereum",
      "score": 61,
      "risk": {
        "level": "medium",
        "reasons": [
          "存在需要进一步核验的风险信号"
        ]
      },
      "summary": "UNCX Network V3 is a growing DeFi protocol with verifiable TVL and yield evidence.",
      "evidence": [
        "$21,585,043.33 TVL",
        "12.63% TVL change over 7 days"
      ],
      "sourceUrl": "https://defillama.com/protocol/uncx-network-v3",
      "observedAt": "2026-07-06T11:58:40.185Z"
    },
    {
      "id": "protocol:4238",
      "kind": "protocol",
      "name": "Zircuit Staking",
      "type": "defi",
      "chain": "Ethereum",
      "score": 61,
      "risk": {
        "level": "medium",
        "reasons": [
          "存在需要进一步核验的风险信号"
        ]
      },
      "summary": "Zircuit Staking is a growing DeFi protocol with verifiable TVL and yield evidence.",
      "evidence": [
        "$42,806,818.62 TVL",
        "10.81% TVL change over 7 days"
      ],
      "sourceUrl": "https://defillama.com/protocol/zircuit-staking",
      "observedAt": "2026-07-06T11:58:40.185Z"
    },
    {
      "id": "protocol:6173",
      "kind": "protocol",
      "name": "Strike Finance Perpetuals",
      "type": "defi",
      "chain": "Ethereum",
      "score": 61,
      "risk": {
        "level": "high",
        "reasons": [
          "存在高优先级风险信号"
        ]
      },
      "summary": "Strike Finance Perpetuals is a growing DeFi protocol with verifiable TVL and yield evidence.",
      "evidence": [
        "$2,394,270.8 TVL",
        "154.62% TVL change over 7 days"
      ],
      "sourceUrl": "https://defillama.com/protocol/strike-finance-perpetuals",
      "observedAt": "2026-07-06T11:58:40.185Z"
    },
    {
      "id": "protocol:6208",
      "kind": "protocol",
      "name": "MEV Capital",
      "type": "defi",
      "chain": "Ethereum",
      "score": 61,
      "risk": {
        "level": "medium",
        "reasons": [
          "存在需要进一步核验的风险信号"
        ]
      },
      "summary": "MEV Capital is a growing DeFi protocol with verifiable TVL and yield evidence.",
      "evidence": [
        "$49,824,650.91 TVL",
        "1.49% TVL change over 7 days"
      ],
      "sourceUrl": "https://defillama.com/protocol/mev-capital",
      "observedAt": "2026-07-06T11:58:40.185Z"
    },
    {
      "id": "protocol:7793",
      "kind": "protocol",
      "name": "Zama",
      "type": "defi",
      "chain": "Ethereum",
      "score": 61,
      "risk": {
        "level": "medium",
        "reasons": [
          "存在需要进一步核验的风险信号"
        ]
      },
      "summary": "Zama is a growing DeFi protocol with verifiable TVL and yield evidence.",
      "evidence": [
        "$36,263,227.48 TVL",
        "12.59% TVL change over 7 days"
      ],
      "sourceUrl": "https://defillama.com/protocol/zama",
      "observedAt": "2026-07-06T11:58:40.185Z"
    },
    {
      "id": "protocol:2081",
      "kind": "protocol",
      "name": "Wan Bridge",
      "type": "defi",
      "chain": "BNB Chain",
      "score": 60,
      "risk": {
        "level": "medium",
        "reasons": [
          "存在需要进一步核验的风险信号"
        ]
      },
      "summary": "Wan Bridge is a growing DeFi protocol with verifiable TVL and yield evidence.",
      "evidence": [
        "$24,839,168.67 TVL",
        "5.16% TVL change over 7 days"
      ],
      "sourceUrl": "https://defillama.com/protocol/wan-bridge",
      "observedAt": "2026-07-06T11:58:40.185Z"
    },
    {
      "id": "protocol:217",
      "kind": "protocol",
      "name": "Connext",
      "type": "defi",
      "chain": "Ethereum",
      "score": 60,
      "risk": {
        "level": "medium",
        "reasons": [
          "存在需要进一步核验的风险信号"
        ]
      },
      "summary": "Connext is a growing DeFi protocol with verifiable TVL and yield evidence.",
      "evidence": [
        "$22,551,245.28 TVL",
        "7.77% TVL change over 7 days"
      ],
      "sourceUrl": "https://defillama.com/protocol/connext",
      "observedAt": "2026-07-06T11:58:40.185Z"
    },
    {
      "id": "protocol:2223",
      "kind": "protocol",
      "name": "Meteora vaults",
      "type": "defi",
      "chain": "Solana",
      "score": 60,
      "risk": {
        "level": "medium",
        "reasons": [
          "存在需要进一步核验的风险信号"
        ]
      },
      "summary": "Meteora vaults is a growing DeFi protocol with verifiable TVL and yield evidence.",
      "evidence": [
        "$44,675,955.68 TVL",
        "7.02% TVL change over 7 days"
      ],
      "sourceUrl": "https://defillama.com/protocol/meteora-vaults",
      "observedAt": "2026-07-06T11:58:40.185Z"
    },
    {
      "id": "protocol:2264",
      "kind": "protocol",
      "name": "Orderly Bridge",
      "type": "defi",
      "chain": "Solana",
      "score": 60,
      "risk": {
        "level": "medium",
        "reasons": [
          "存在需要进一步核验的风险信号"
        ]
      },
      "summary": "Orderly Bridge is a growing DeFi protocol with verifiable TVL and yield evidence.",
      "evidence": [
        "$22,594,510.06 TVL",
        "6.53% TVL change over 7 days"
      ],
      "sourceUrl": "https://defillama.com/protocol/orderly-bridge",
      "observedAt": "2026-07-06T11:58:40.185Z"
    },
    {
      "id": "protocol:2402",
      "kind": "protocol",
      "name": "Veno Finance",
      "type": "defi",
      "chain": "Ethereum",
      "score": 60,
      "risk": {
        "level": "medium",
        "reasons": [
          "存在需要进一步核验的风险信号"
        ]
      },
      "summary": "Veno Finance is a growing DeFi protocol with verifiable TVL and yield evidence.",
      "evidence": [
        "$36,306,306.86 TVL",
        "8.56% TVL change over 7 days"
      ],
      "sourceUrl": "https://defillama.com/protocol/veno-finance",
      "observedAt": "2026-07-06T11:58:40.185Z"
    },
    {
      "id": "protocol:385",
      "kind": "protocol",
      "name": "Meteora DAMM V1",
      "type": "defi",
      "chain": "Solana",
      "score": 60,
      "risk": {
        "level": "medium",
        "reasons": [
          "存在需要进一步核验的风险信号"
        ]
      },
      "summary": "Meteora DAMM V1 is a growing DeFi protocol with verifiable TVL and yield evidence.",
      "evidence": [
        "$40,738,734.64 TVL",
        "7.34% TVL change over 7 days"
      ],
      "sourceUrl": "https://defillama.com/protocol/meteora-damm-v1",
      "observedAt": "2026-07-06T11:58:40.185Z"
    },
    {
      "id": "protocol:4058",
      "kind": "protocol",
      "name": "Brickken",
      "type": "defi",
      "chain": "BNB Chain",
      "score": 60,
      "risk": {
        "level": "medium",
        "reasons": [
          "存在需要进一步核验的风险信号"
        ]
      },
      "summary": "Brickken is a growing DeFi protocol with verifiable TVL and yield evidence.",
      "evidence": [
        "$42,358,246.57 TVL",
        "0.47% TVL change over 7 days"
      ],
      "sourceUrl": "https://defillama.com/protocol/brickken",
      "observedAt": "2026-07-06T11:58:40.185Z"
    },
    {
      "id": "protocol:4236",
      "kind": "protocol",
      "name": "Blast Bridge",
      "type": "defi",
      "chain": "Ethereum",
      "score": 60,
      "risk": {
        "level": "medium",
        "reasons": [
          "存在需要进一步核验的风险信号"
        ]
      },
      "summary": "Blast Bridge is a growing DeFi protocol with verifiable TVL and yield evidence.",
      "evidence": [
        "$49,153,338.85 TVL",
        "6.81% TVL change over 7 days"
      ],
      "sourceUrl": "https://defillama.com/protocol/blast-bridge",
      "observedAt": "2026-07-06T11:58:40.185Z"
    },
    {
      "id": "protocol:4822",
      "kind": "protocol",
      "name": "Apex Omni",
      "type": "defi",
      "chain": "Ethereum",
      "score": 60,
      "risk": {
        "level": "medium",
        "reasons": [
          "存在需要进一步核验的风险信号"
        ]
      },
      "summary": "Apex Omni is a growing DeFi protocol with verifiable TVL and yield evidence.",
      "evidence": [
        "$33,462,332.93 TVL",
        "2.35% TVL change over 7 days"
      ],
      "sourceUrl": "https://defillama.com/protocol/apex-omni",
      "observedAt": "2026-07-06T11:58:40.185Z"
    },
    {
      "id": "protocol:5143",
      "kind": "protocol",
      "name": "Lombard Vaults",
      "type": "defi",
      "chain": "Ethereum",
      "score": 60,
      "risk": {
        "level": "medium",
        "reasons": [
          "存在需要进一步核验的风险信号"
        ]
      },
      "summary": "Lombard Vaults is a growing DeFi protocol with verifiable TVL and yield evidence.",
      "evidence": [
        "$36,981,289.48 TVL",
        "3.11% TVL change over 7 days"
      ],
      "sourceUrl": "https://defillama.com/protocol/lombard-vaults",
      "observedAt": "2026-07-06T11:58:40.185Z"
    },
    {
      "id": "protocol:5683",
      "kind": "protocol",
      "name": "Sonic Gateway",
      "type": "defi",
      "chain": "Ethereum",
      "score": 60,
      "risk": {
        "level": "medium",
        "reasons": [
          "存在需要进一步核验的风险信号"
        ]
      },
      "summary": "Sonic Gateway is a growing DeFi protocol with verifiable TVL and yield evidence.",
      "evidence": [
        "$40,073,422.06 TVL",
        "9.23% TVL change over 7 days"
      ],
      "sourceUrl": "https://defillama.com/protocol/sonic-gateway",
      "observedAt": "2026-07-06T11:58:40.185Z"
    },
    {
      "id": "protocol:5899",
      "kind": "protocol",
      "name": "Bitbond Lockers",
      "type": "defi",
      "chain": "BNB Chain",
      "score": 60,
      "risk": {
        "level": "medium",
        "reasons": [
          "存在需要进一步核验的风险信号"
        ]
      },
      "summary": "Bitbond Lockers is a growing DeFi protocol with verifiable TVL and yield evidence.",
      "evidence": [
        "$9,472,208.2 TVL",
        "18.38% TVL change over 7 days"
      ],
      "sourceUrl": "https://defillama.com/protocol/bitbond-lockers",
      "observedAt": "2026-07-06T11:58:40.185Z"
    },
    {
      "id": "protocol:6198",
      "kind": "protocol",
      "name": "Block Analitica",
      "type": "defi",
      "chain": "Ethereum",
      "score": 60,
      "risk": {
        "level": "medium",
        "reasons": [
          "存在需要进一步核验的风险信号"
        ]
      },
      "summary": "Block Analitica is a growing DeFi protocol with verifiable TVL and yield evidence.",
      "evidence": [
        "$42,195,159.14 TVL",
        "6.13% TVL change over 7 days"
      ],
      "sourceUrl": "https://defillama.com/protocol/block-analitica",
      "observedAt": "2026-07-06T11:58:40.185Z"
    },
    {
      "id": "protocol:636",
      "kind": "protocol",
      "name": "Keep3r Network",
      "type": "defi",
      "chain": "Ethereum",
      "score": 60,
      "risk": {
        "level": "high",
        "reasons": [
          "存在高优先级风险信号"
        ]
      },
      "summary": "Keep3r Network is a growing DeFi protocol with verifiable TVL and yield evidence.",
      "evidence": [
        "$2,999,588.45 TVL",
        "303.64% TVL change over 7 days"
      ],
      "sourceUrl": "https://defillama.com/protocol/keep3r-network",
      "observedAt": "2026-07-06T11:58:40.185Z"
    },
    {
      "id": "protocol:6570",
      "kind": "protocol",
      "name": "Templar Protocol",
      "type": "defi",
      "chain": "Ethereum",
      "score": 60,
      "risk": {
        "level": "medium",
        "reasons": [
          "存在需要进一步核验的风险信号"
        ]
      },
      "summary": "Templar Protocol is a growing DeFi protocol with verifiable TVL and yield evidence.",
      "evidence": [
        "$23,330,921.33 TVL",
        "9.44% TVL change over 7 days"
      ],
      "sourceUrl": "https://defillama.com/protocol/templar-protocol",
      "observedAt": "2026-07-06T11:58:40.185Z"
    },
    {
      "id": "protocol:6784",
      "kind": "protocol",
      "name": "Legion",
      "type": "defi",
      "chain": "Ethereum",
      "score": 60,
      "risk": {
        "level": "high",
        "reasons": [
          "存在高优先级风险信号"
        ]
      },
      "summary": "Legion is a growing DeFi protocol with verifiable TVL and yield evidence.",
      "evidence": [
        "$6,408,663.56 TVL",
        "963.32% TVL change over 7 days"
      ],
      "sourceUrl": "https://defillama.com/protocol/legion",
      "observedAt": "2026-07-06T11:58:40.185Z"
    },
    {
      "id": "protocol:8063",
      "kind": "protocol",
      "name": "Tori Finance",
      "type": "defi",
      "chain": "Ethereum",
      "score": 60,
      "risk": {
        "level": "medium",
        "reasons": [
          "存在需要进一步核验的风险信号"
        ]
      },
      "summary": "Tori Finance is a growing DeFi protocol with verifiable TVL and yield evidence.",
      "evidence": [
        "$49,989,722.33 TVL",
        "4.37% TVL change over 7 days"
      ],
      "sourceUrl": "https://defillama.com/protocol/tori-finance",
      "observedAt": "2026-07-06T11:58:40.185Z"
    },
    {
      "id": "protocol:1339",
      "kind": "protocol",
      "name": "Api3",
      "type": "defi",
      "chain": "Ethereum",
      "score": 59,
      "risk": {
        "level": "medium",
        "reasons": [
          "存在需要进一步核验的风险信号"
        ]
      },
      "summary": "Api3 is a growing DeFi protocol with verifiable TVL and yield evidence.",
      "evidence": [
        "$17,561,343.3 TVL",
        "14.27% TVL change over 7 days"
      ],
      "sourceUrl": "https://defillama.com/protocol/api3",
      "observedAt": "2026-07-06T11:58:40.185Z"
    },
    {
      "id": "protocol:2428",
      "kind": "protocol",
      "name": "Metronome Synth",
      "type": "defi",
      "chain": "Ethereum",
      "score": 59,
      "risk": {
        "level": "medium",
        "reasons": [
          "存在需要进一步核验的风险信号"
        ]
      },
      "summary": "Metronome Synth is a growing DeFi protocol with verifiable TVL and yield evidence.",
      "evidence": [
        "$20,598,488.82 TVL",
        "12.33% TVL change over 7 days"
      ],
      "sourceUrl": "https://defillama.com/protocol/metronome-synth",
      "observedAt": "2026-07-06T11:58:40.185Z"
    },
    {
      "id": "protocol:2570",
      "kind": "protocol",
      "name": "marginfi Lending",
      "type": "defi",
      "chain": "Solana",
      "score": 59,
      "risk": {
        "level": "medium",
        "reasons": [
          "存在需要进一步核验的风险信号"
        ]
      },
      "summary": "marginfi Lending is a growing DeFi protocol with verifiable TVL and yield evidence.",
      "evidence": [
        "$33,621,650.9 TVL",
        "7.5% TVL change over 7 days"
      ],
      "sourceUrl": "https://defillama.com/protocol/marginfi-lending",
      "observedAt": "2026-07-06T11:58:40.185Z"
    },
    {
      "id": "protocol:4158",
      "kind": "protocol",
      "name": "Crypto.com Liquid Staking",
      "type": "defi",
      "chain": "Solana",
      "score": 59,
      "risk": {
        "level": "medium",
        "reasons": [
          "存在需要进一步核验的风险信号"
        ]
      },
      "summary": "Crypto.com Liquid Staking is a growing DeFi protocol with verifiable TVL and yield evidence.",
      "evidence": [
        "$21,656,136.96 TVL",
        "10.97% TVL change over 7 days"
      ],
      "sourceUrl": "https://defillama.com/protocol/crypto.com-liquid-staking",
      "observedAt": "2026-07-06T11:58:40.185Z"
    },
    {
      "id": "protocol:4439",
      "kind": "protocol",
      "name": "PulseChain Bridge",
      "type": "defi",
      "chain": "Ethereum",
      "score": 59,
      "risk": {
        "level": "medium",
        "reasons": [
          "存在需要进一步核验的风险信号"
        ]
      },
      "summary": "PulseChain Bridge is a growing DeFi protocol with verifiable TVL and yield evidence.",
      "evidence": [
        "$49,343,289.35 TVL",
        "3.19% TVL change over 7 days"
      ],
      "sourceUrl": "https://defillama.com/protocol/pulsechain-bridge",
      "observedAt": "2026-07-06T11:58:40.185Z"
    },
    {
      "id": "protocol:4756",
      "kind": "protocol",
      "name": "Mellow Restaking",
      "type": "defi",
      "chain": "Ethereum",
      "score": 59,
      "risk": {
        "level": "medium",
        "reasons": [
          "存在需要进一步核验的风险信号"
        ]
      },
      "summary": "Mellow Restaking is a growing DeFi protocol with verifiable TVL and yield evidence.",
      "evidence": [
        "$20,337,348.54 TVL",
        "6.67% TVL change over 7 days"
      ],
      "sourceUrl": "https://defillama.com/protocol/mellow-restaking",
      "observedAt": "2026-07-06T11:58:40.185Z"
    },
    {
      "id": "protocol:5909",
      "kind": "protocol",
      "name": "GoPlus Locker V3",
      "type": "defi",
      "chain": "BNB Chain",
      "score": 59,
      "risk": {
        "level": "medium",
        "reasons": [
          "存在需要进一步核验的风险信号"
        ]
      },
      "summary": "GoPlus Locker V3 is a growing DeFi protocol with verifiable TVL and yield evidence.",
      "evidence": [
        "$26,509,560.77 TVL",
        "3.8% TVL change over 7 days"
      ],
      "sourceUrl": "https://defillama.com/protocol/goplus-locker-v3",
      "observedAt": "2026-07-06T11:58:40.185Z"
    },
    {
      "id": "protocol:1901",
      "kind": "protocol",
      "name": "DxSale",
      "type": "defi",
      "chain": "BNB Chain",
      "score": 58,
      "risk": {
        "level": "medium",
        "reasons": [
          "存在需要进一步核验的风险信号"
        ]
      },
      "summary": "DxSale is a growing DeFi protocol with verifiable TVL and yield evidence.",
      "evidence": [
        "$16,098,859.54 TVL",
        "4.53% TVL change over 7 days"
      ],
      "sourceUrl": "https://defillama.com/protocol/dxsale",
      "observedAt": "2026-07-06T11:58:40.185Z"
    },
    {
      "id": "protocol:1981",
      "kind": "protocol",
      "name": "Orbit Bridge",
      "type": "defi",
      "chain": "BNB Chain",
      "score": 58,
      "risk": {
        "level": "medium",
        "reasons": [
          "存在需要进一步核验的风险信号"
        ]
      },
      "summary": "Orbit Bridge is a growing DeFi protocol with verifiable TVL and yield evidence.",
      "evidence": [
        "$15,392,454.67 TVL",
        "4.88% TVL change over 7 days"
      ],
      "sourceUrl": "https://defillama.com/protocol/orbit-bridge",
      "observedAt": "2026-07-06T11:58:40.185Z"
    }
  ]
}
