{
  "generatedAt": "2026-07-12T16:52:28.179Z",
  "stale": false,
  "sourceStatus": {
    "dexscreener": {
      "status": "ok",
      "observedAt": "2026-07-12T16:52:28.179Z"
    },
    "defillama": {
      "status": "ok",
      "observedAt": "2026-07-12T16:52:28.179Z"
    },
    "rpc": {
      "status": "ok",
      "observedAt": "2026-07-12T16:52:28.179Z"
    }
  },
  "chainHeads": {
    "ethereum": {
      "height": 25517855,
      "observedAt": "2026-07-12T16:52:28.520Z",
      "status": "ok"
    },
    "bsc": {
      "height": 109590788,
      "observedAt": "2026-07-12T16:52:28.776Z",
      "status": "ok"
    },
    "solana": {
      "height": 432471424,
      "observedAt": "2026-07-12T16:52:29.116Z",
      "status": "ok"
    }
  },
  "marketIndex": 63,
  "signalCount": 100,
  "disclaimer": "Research data only. AlphaOS does not provide financial advice.",
  "opportunities": [
    {
      "id": "protocol:4799",
      "kind": "protocol",
      "name": "TermMax",
      "type": "defi",
      "chain": "Ethereum",
      "score": 83,
      "risk": {
        "level": "low",
        "reasons": [
          "未发现高优先级风险信号"
        ]
      },
      "summary": "TermMax is a growing DeFi protocol with verifiable TVL and yield evidence.",
      "evidence": [
        "$33,530,863.75 TVL",
        "12.87% TVL change over 7 days"
      ],
      "sourceUrl": "https://defillama.com/protocol/termmax",
      "observedAt": "2026-07-12T16:52:28.179Z"
    },
    {
      "id": "protocol:438",
      "kind": "protocol",
      "name": "AUTOfinance",
      "type": "defi",
      "chain": "Ethereum",
      "score": 82,
      "risk": {
        "level": "low",
        "reasons": [
          "未发现高优先级风险信号"
        ]
      },
      "summary": "AUTOfinance is a growing DeFi protocol with verifiable TVL and yield evidence.",
      "evidence": [
        "$35,619,805.84 TVL",
        "15.84% TVL change over 7 days"
      ],
      "sourceUrl": "https://defillama.com/protocol/autofinance",
      "observedAt": "2026-07-12T16:52:28.179Z"
    },
    {
      "id": "protocol:2776",
      "kind": "protocol",
      "name": "SushiSwap V3",
      "type": "defi",
      "chain": "Ethereum",
      "score": 80,
      "risk": {
        "level": "low",
        "reasons": [
          "未发现高优先级风险信号"
        ]
      },
      "summary": "SushiSwap V3 is a growing DeFi protocol with verifiable TVL and yield evidence.",
      "evidence": [
        "$37,879,178.37 TVL",
        "0.99% TVL change over 7 days"
      ],
      "sourceUrl": "https://defillama.com/protocol/sushiswap-v3",
      "observedAt": "2026-07-12T16:52:28.179Z"
    },
    {
      "id": "protocol:5145",
      "kind": "protocol",
      "name": "Fusion by IPOR",
      "type": "defi",
      "chain": "Ethereum",
      "score": 80,
      "risk": {
        "level": "low",
        "reasons": [
          "未发现高优先级风险信号"
        ]
      },
      "summary": "Fusion by IPOR is a growing DeFi protocol with verifiable TVL and yield evidence.",
      "evidence": [
        "$38,137,850.37 TVL",
        "7.48% TVL change over 7 days"
      ],
      "sourceUrl": "https://defillama.com/protocol/fusion-by-ipor",
      "observedAt": "2026-07-12T16:52:28.179Z"
    },
    {
      "id": "protocol:1108",
      "kind": "protocol",
      "name": "Gearbox",
      "type": "defi",
      "chain": "Ethereum",
      "score": 78,
      "risk": {
        "level": "low",
        "reasons": [
          "未发现高优先级风险信号"
        ]
      },
      "summary": "Gearbox is a growing DeFi protocol with verifiable TVL and yield evidence.",
      "evidence": [
        "$18,673,875.62 TVL",
        "3.57% TVL change over 7 days"
      ],
      "sourceUrl": "https://defillama.com/protocol/gearbox",
      "observedAt": "2026-07-12T16:52:28.179Z"
    },
    {
      "id": "protocol:2537",
      "kind": "protocol",
      "name": "Flux Finance",
      "type": "defi",
      "chain": "Ethereum",
      "score": 78,
      "risk": {
        "level": "low",
        "reasons": [
          "未发现高优先级风险信号"
        ]
      },
      "summary": "Flux Finance is a growing DeFi protocol with verifiable TVL and yield evidence.",
      "evidence": [
        "$44,216,152.23 TVL",
        "0.01% TVL change over 7 days"
      ],
      "sourceUrl": "https://defillama.com/protocol/flux-finance",
      "observedAt": "2026-07-12T16:52:28.179Z"
    },
    {
      "id": "protocol:6024",
      "kind": "protocol",
      "name": "Aegis YUSD",
      "type": "defi",
      "chain": "Ethereum",
      "score": 78,
      "risk": {
        "level": "low",
        "reasons": [
          "未发现高优先级风险信号"
        ]
      },
      "summary": "Aegis YUSD is a growing DeFi protocol with verifiable TVL and yield evidence.",
      "evidence": [
        "$35,821,616.17 TVL",
        "0.08% TVL change over 7 days"
      ],
      "sourceUrl": "https://defillama.com/protocol/aegis-yusd",
      "observedAt": "2026-07-12T16:52:28.179Z"
    },
    {
      "id": "protocol:1207",
      "kind": "protocol",
      "name": "Across",
      "type": "defi",
      "chain": "Ethereum",
      "score": 77,
      "risk": {
        "level": "low",
        "reasons": [
          "未发现高优先级风险信号"
        ]
      },
      "summary": "Across is a growing DeFi protocol with verifiable TVL and yield evidence.",
      "evidence": [
        "$20,958,592.11 TVL",
        "4.45% TVL change over 7 days"
      ],
      "sourceUrl": "https://defillama.com/protocol/across",
      "observedAt": "2026-07-12T16:52:28.179Z"
    },
    {
      "id": "protocol:278",
      "kind": "protocol",
      "name": "Ankr",
      "type": "defi",
      "chain": "Ethereum",
      "score": 77,
      "risk": {
        "level": "low",
        "reasons": [
          "未发现高优先级风险信号"
        ]
      },
      "summary": "Ankr is a growing DeFi protocol with verifiable TVL and yield evidence.",
      "evidence": [
        "$19,537,391.72 TVL",
        "0.94% TVL change over 7 days"
      ],
      "sourceUrl": "https://defillama.com/protocol/ankr",
      "observedAt": "2026-07-12T16:52:28.179Z"
    },
    {
      "id": "protocol:2993",
      "kind": "protocol",
      "name": "NodeDAO",
      "type": "defi",
      "chain": "Ethereum",
      "score": 77,
      "risk": {
        "level": "low",
        "reasons": [
          "未发现高优先级风险信号"
        ]
      },
      "summary": "NodeDAO is a growing DeFi protocol with verifiable TVL and yield evidence.",
      "evidence": [
        "$25,802,842.16 TVL",
        "2.68% TVL change over 7 days"
      ],
      "sourceUrl": "https://defillama.com/protocol/nodedao",
      "observedAt": "2026-07-12T16:52:28.179Z"
    },
    {
      "id": "protocol:4606",
      "kind": "protocol",
      "name": "YieldNest",
      "type": "defi",
      "chain": "Ethereum",
      "score": 77,
      "risk": {
        "level": "low",
        "reasons": [
          "未发现高优先级风险信号"
        ]
      },
      "summary": "YieldNest is a growing DeFi protocol with verifiable TVL and yield evidence.",
      "evidence": [
        "$20,198,413.23 TVL",
        "1.15% TVL change over 7 days"
      ],
      "sourceUrl": "https://defillama.com/protocol/yieldnest",
      "observedAt": "2026-07-12T16:52:28.179Z"
    },
    {
      "id": "protocol:6964",
      "kind": "protocol",
      "name": "Makina",
      "type": "defi",
      "chain": "Ethereum",
      "score": 77,
      "risk": {
        "level": "low",
        "reasons": [
          "未发现高优先级风险信号"
        ]
      },
      "summary": "Makina is a growing DeFi protocol with verifiable TVL and yield evidence.",
      "evidence": [
        "$36,596,925.97 TVL",
        "0.28% TVL change over 7 days"
      ],
      "sourceUrl": "https://defillama.com/protocol/makina",
      "observedAt": "2026-07-12T16:52:28.179Z"
    },
    {
      "id": "protocol:7297",
      "kind": "protocol",
      "name": "GMTrade",
      "type": "defi",
      "chain": "Solana",
      "score": 77,
      "risk": {
        "level": "low",
        "reasons": [
          "未发现高优先级风险信号"
        ]
      },
      "summary": "GMTrade is a growing DeFi protocol with verifiable TVL and yield evidence.",
      "evidence": [
        "$35,647,449.28 TVL",
        "0.75% TVL change over 7 days"
      ],
      "sourceUrl": "https://defillama.com/protocol/gmtrade",
      "observedAt": "2026-07-12T16:52:28.179Z"
    },
    {
      "id": "protocol:1594",
      "kind": "protocol",
      "name": "Symbiosis",
      "type": "defi",
      "chain": "Ethereum",
      "score": 76,
      "risk": {
        "level": "low",
        "reasons": [
          "未发现高优先级风险信号"
        ]
      },
      "summary": "Symbiosis is a growing DeFi protocol with verifiable TVL and yield evidence.",
      "evidence": [
        "$9,318,903.13 TVL",
        "4.48% TVL change over 7 days"
      ],
      "sourceUrl": "https://defillama.com/protocol/symbiosis",
      "observedAt": "2026-07-12T16:52:28.179Z"
    },
    {
      "id": "protocol:2076",
      "kind": "protocol",
      "name": "Fraxlend",
      "type": "defi",
      "chain": "Ethereum",
      "score": 76,
      "risk": {
        "level": "low",
        "reasons": [
          "未发现高优先级风险信号"
        ]
      },
      "summary": "Fraxlend is a growing DeFi protocol with verifiable TVL and yield evidence.",
      "evidence": [
        "$20,822,285.18 TVL",
        "1.66% TVL change over 7 days"
      ],
      "sourceUrl": "https://defillama.com/protocol/fraxlend",
      "observedAt": "2026-07-12T16:52:28.179Z"
    },
    {
      "id": "protocol:3405",
      "kind": "protocol",
      "name": "Meta Pool ETH",
      "type": "defi",
      "chain": "Ethereum",
      "score": 76,
      "risk": {
        "level": "low",
        "reasons": [
          "未发现高优先级风险信号"
        ]
      },
      "summary": "Meta Pool ETH is a growing DeFi protocol with verifiable TVL and yield evidence.",
      "evidence": [
        "$19,010,215.74 TVL",
        "2.43% TVL change over 7 days"
      ],
      "sourceUrl": "https://defillama.com/protocol/meta-pool-eth",
      "observedAt": "2026-07-12T16:52:28.179Z"
    },
    {
      "id": "protocol:3871",
      "kind": "protocol",
      "name": "Wildcat Protocol",
      "type": "defi",
      "chain": "Ethereum",
      "score": 76,
      "risk": {
        "level": "low",
        "reasons": [
          "未发现高优先级风险信号"
        ]
      },
      "summary": "Wildcat Protocol is a growing DeFi protocol with verifiable TVL and yield evidence.",
      "evidence": [
        "$10,514,044.97 TVL",
        "9.68% TVL change over 7 days"
      ],
      "sourceUrl": "https://defillama.com/protocol/wildcat-protocol",
      "observedAt": "2026-07-12T16:52:28.179Z"
    },
    {
      "id": "protocol:2433",
      "kind": "protocol",
      "name": "Inverse Finance FiRM",
      "type": "defi",
      "chain": "Ethereum",
      "score": 75,
      "risk": {
        "level": "low",
        "reasons": [
          "未发现高优先级风险信号"
        ]
      },
      "summary": "Inverse Finance FiRM is a growing DeFi protocol with verifiable TVL and yield evidence.",
      "evidence": [
        "$18,814,672.27 TVL",
        "0.13% TVL change over 7 days"
      ],
      "sourceUrl": "https://defillama.com/protocol/inverse-finance-firm",
      "observedAt": "2026-07-12T16:52:28.179Z"
    },
    {
      "id": "protocol:3499",
      "kind": "protocol",
      "name": "Ekubo",
      "type": "defi",
      "chain": "Ethereum",
      "score": 75,
      "risk": {
        "level": "low",
        "reasons": [
          "未发现高优先级风险信号"
        ]
      },
      "summary": "Ekubo is a growing DeFi protocol with verifiable TVL and yield evidence.",
      "evidence": [
        "$23,698,447.83 TVL",
        "5.7% TVL change over 7 days"
      ],
      "sourceUrl": "https://defillama.com/protocol/ekubo",
      "observedAt": "2026-07-12T16:52:28.179Z"
    },
    {
      "id": "protocol:4088",
      "kind": "protocol",
      "name": "Puffer Stake",
      "type": "defi",
      "chain": "Ethereum",
      "score": 74,
      "risk": {
        "level": "low",
        "reasons": [
          "未发现高优先级风险信号"
        ]
      },
      "summary": "Puffer Stake is a growing DeFi protocol with verifiable TVL and yield evidence.",
      "evidence": [
        "$44,492,452.59 TVL",
        "2.27% TVL change over 7 days"
      ],
      "sourceUrl": "https://defillama.com/protocol/puffer-stake",
      "observedAt": "2026-07-12T16:52:28.179Z"
    },
    {
      "id": "protocol:2611",
      "kind": "protocol",
      "name": "Balancer V2",
      "type": "defi",
      "chain": "Ethereum",
      "score": 73,
      "risk": {
        "level": "low",
        "reasons": [
          "未发现高优先级风险信号"
        ]
      },
      "summary": "Balancer V2 is a growing DeFi protocol with verifiable TVL and yield evidence.",
      "evidence": [
        "$29,075,231.32 TVL",
        "4.89% TVL change over 7 days"
      ],
      "sourceUrl": "https://defillama.com/protocol/balancer-v2",
      "observedAt": "2026-07-12T16:52:28.179Z"
    },
    {
      "id": "protocol:5995",
      "kind": "protocol",
      "name": "OpenEden USDO",
      "type": "defi",
      "chain": "Ethereum",
      "score": 73,
      "risk": {
        "level": "low",
        "reasons": [
          "未发现高优先级风险信号"
        ]
      },
      "summary": "OpenEden USDO is a growing DeFi protocol with verifiable TVL and yield evidence.",
      "evidence": [
        "$28,350,255.58 TVL",
        "0.64% TVL change over 7 days"
      ],
      "sourceUrl": "https://defillama.com/protocol/openeden-usdo",
      "observedAt": "2026-07-12T16:52:28.179Z"
    },
    {
      "id": "protocol:6535",
      "kind": "protocol",
      "name": "GAIB",
      "type": "defi",
      "chain": "Ethereum",
      "score": 72,
      "risk": {
        "level": "low",
        "reasons": [
          "未发现高优先级风险信号"
        ]
      },
      "summary": "GAIB is a growing DeFi protocol with verifiable TVL and yield evidence.",
      "evidence": [
        "$20,158,429.11 TVL",
        "0.84% TVL change over 7 days"
      ],
      "sourceUrl": "https://defillama.com/protocol/gaib",
      "observedAt": "2026-07-12T16:52:28.179Z"
    },
    {
      "id": "protocol:2901",
      "kind": "protocol",
      "name": "Swell Liquid Staking",
      "type": "defi",
      "chain": "Ethereum",
      "score": 71,
      "risk": {
        "level": "low",
        "reasons": [
          "未发现高优先级风险信号"
        ]
      },
      "summary": "Swell Liquid Staking is a growing DeFi protocol with verifiable TVL and yield evidence.",
      "evidence": [
        "$24,875,523.71 TVL",
        "1.99% TVL change over 7 days"
      ],
      "sourceUrl": "https://defillama.com/protocol/swell-liquid-staking",
      "observedAt": "2026-07-12T16:52:28.179Z"
    },
    {
      "id": "protocol:4078",
      "kind": "protocol",
      "name": "Swell Liquid Restaking",
      "type": "defi",
      "chain": "Ethereum",
      "score": 71,
      "risk": {
        "level": "low",
        "reasons": [
          "未发现高优先级风险信号"
        ]
      },
      "summary": "Swell Liquid Restaking is a growing DeFi protocol with verifiable TVL and yield evidence.",
      "evidence": [
        "$22,609,843.54 TVL",
        "1.66% TVL change over 7 days"
      ],
      "sourceUrl": "https://defillama.com/protocol/swell-liquid-restaking",
      "observedAt": "2026-07-12T16:52:28.179Z"
    },
    {
      "id": "protocol:2832",
      "kind": "protocol",
      "name": "Bedrock uniETH",
      "type": "defi",
      "chain": "Ethereum",
      "score": 70,
      "risk": {
        "level": "low",
        "reasons": [
          "未发现高优先级风险信号"
        ]
      },
      "summary": "Bedrock uniETH is a growing DeFi protocol with verifiable TVL and yield evidence.",
      "evidence": [
        "$18,787,891.41 TVL",
        "1.86% TVL change over 7 days"
      ],
      "sourceUrl": "https://defillama.com/protocol/bedrock-unieth",
      "observedAt": "2026-07-12T16:52:28.179Z"
    },
    {
      "id": "protocol:6905",
      "kind": "protocol",
      "name": "Avant avETH",
      "type": "defi",
      "chain": "Ethereum",
      "score": 70,
      "risk": {
        "level": "low",
        "reasons": [
          "未发现高优先级风险信号"
        ]
      },
      "summary": "Avant avETH is a growing DeFi protocol with verifiable TVL and yield evidence.",
      "evidence": [
        "$16,490,692.65 TVL",
        "1.82% TVL change over 7 days"
      ],
      "sourceUrl": "https://defillama.com/protocol/avant-aveth",
      "observedAt": "2026-07-12T16:52:28.179Z"
    },
    {
      "id": "protocol:112",
      "kind": "protocol",
      "name": "Harvest Finance",
      "type": "defi",
      "chain": "Ethereum",
      "score": 69,
      "risk": {
        "level": "low",
        "reasons": [
          "未发现高优先级风险信号"
        ]
      },
      "summary": "Harvest Finance is a growing DeFi protocol with verifiable TVL and yield evidence.",
      "evidence": [
        "$12,000,114.64 TVL",
        "2.84% TVL change over 7 days"
      ],
      "sourceUrl": "https://defillama.com/protocol/harvest-finance",
      "observedAt": "2026-07-12T16:52:28.179Z"
    },
    {
      "id": "protocol:2454",
      "kind": "protocol",
      "name": "GETH",
      "type": "defi",
      "chain": "Ethereum",
      "score": 69,
      "risk": {
        "level": "low",
        "reasons": [
          "未发现高优先级风险信号"
        ]
      },
      "summary": "GETH is a growing DeFi protocol with verifiable TVL and yield evidence.",
      "evidence": [
        "$13,839,088.27 TVL",
        "2.27% TVL change over 7 days"
      ],
      "sourceUrl": "https://defillama.com/protocol/geth",
      "observedAt": "2026-07-12T16:52:28.179Z"
    },
    {
      "id": "protocol:577",
      "kind": "protocol",
      "name": "Allbridge Classic",
      "type": "defi",
      "chain": "Ethereum",
      "score": 68,
      "risk": {
        "level": "medium",
        "reasons": [
          "存在需要进一步核验的风险信号"
        ]
      },
      "summary": "Allbridge Classic is a growing DeFi protocol with verifiable TVL and yield evidence.",
      "evidence": [
        "$1,155,552.25 TVL",
        "0.06% TVL change over 7 days"
      ],
      "sourceUrl": "https://defillama.com/protocol/allbridge-classic",
      "observedAt": "2026-07-12T16:52:28.179Z"
    },
    {
      "id": "protocol:173",
      "kind": "protocol",
      "name": "Badger DAO",
      "type": "defi",
      "chain": "Ethereum",
      "score": 65,
      "risk": {
        "level": "medium",
        "reasons": [
          "存在需要进一步核验的风险信号"
        ]
      },
      "summary": "Badger DAO is a growing DeFi protocol with verifiable TVL and yield evidence.",
      "evidence": [
        "$10,379,827.21 TVL",
        "31.93% TVL change over 7 days"
      ],
      "sourceUrl": "https://defillama.com/protocol/badger-dao",
      "observedAt": "2026-07-12T16:52:28.179Z"
    },
    {
      "id": "protocol:3912",
      "kind": "protocol",
      "name": "Dinero (pxETH)",
      "type": "defi",
      "chain": "Ethereum",
      "score": 65,
      "risk": {
        "level": "medium",
        "reasons": [
          "存在需要进一步核验的风险信号"
        ]
      },
      "summary": "Dinero (pxETH) is a growing DeFi protocol with verifiable TVL and yield evidence.",
      "evidence": [
        "$4,189,871.27 TVL",
        "2.09% TVL change over 7 days"
      ],
      "sourceUrl": "https://defillama.com/protocol/dinero-(pxeth)",
      "observedAt": "2026-07-12T16:52:28.179Z"
    },
    {
      "id": "protocol:151",
      "kind": "protocol",
      "name": "Rhino.fi",
      "type": "defi",
      "chain": "Ethereum",
      "score": 64,
      "risk": {
        "level": "medium",
        "reasons": [
          "存在需要进一步核验的风险信号"
        ]
      },
      "summary": "Rhino.fi is a growing DeFi protocol with verifiable TVL and yield evidence.",
      "evidence": [
        "$2,553,616.02 TVL",
        "99.13% TVL change over 7 days"
      ],
      "sourceUrl": "https://defillama.com/protocol/rhino.fi",
      "observedAt": "2026-07-12T16:52:28.179Z"
    },
    {
      "id": "protocol:6504",
      "kind": "protocol",
      "name": "Bracket Vaults",
      "type": "defi",
      "chain": "Ethereum",
      "score": 64,
      "risk": {
        "level": "medium",
        "reasons": [
          "存在需要进一步核验的风险信号"
        ]
      },
      "summary": "Bracket Vaults is a growing DeFi protocol with verifiable TVL and yield evidence.",
      "evidence": [
        "$2,866,029.97 TVL",
        "3.88% TVL change over 7 days"
      ],
      "sourceUrl": "https://defillama.com/protocol/bracket-vaults",
      "observedAt": "2026-07-12T16:52:28.179Z"
    },
    {
      "id": "protocol:6864",
      "kind": "protocol",
      "name": "mStable V2",
      "type": "defi",
      "chain": "Ethereum",
      "score": 64,
      "risk": {
        "level": "medium",
        "reasons": [
          "存在需要进一步核验的风险信号"
        ]
      },
      "summary": "mStable V2 is a growing DeFi protocol with verifiable TVL and yield evidence.",
      "evidence": [
        "$3,321,383.22 TVL",
        "0.71% TVL change over 7 days"
      ],
      "sourceUrl": "https://defillama.com/protocol/mstable-v2",
      "observedAt": "2026-07-12T16:52:28.179Z"
    },
    {
      "id": "protocol:6923",
      "kind": "protocol",
      "name": "Asseto CASH+",
      "type": "defi",
      "chain": "Ethereum",
      "score": 64,
      "risk": {
        "level": "medium",
        "reasons": [
          "存在需要进一步核验的风险信号"
        ]
      },
      "summary": "Asseto CASH+ is a growing DeFi protocol with verifiable TVL and yield evidence.",
      "evidence": [
        "$1,679,973.1 TVL",
        "90.83% TVL change over 7 days"
      ],
      "sourceUrl": "https://defillama.com/protocol/asseto-cash%2B",
      "observedAt": "2026-07-12T16:52:28.179Z"
    },
    {
      "id": "protocol:7663",
      "kind": "protocol",
      "name": "Everything",
      "type": "defi",
      "chain": "Ethereum",
      "score": 63,
      "risk": {
        "level": "medium",
        "reasons": [
          "存在需要进一步核验的风险信号"
        ]
      },
      "summary": "Everything is a growing DeFi protocol with verifiable TVL and yield evidence.",
      "evidence": [
        "$1,346,155.59 TVL",
        "8.36% TVL change over 7 days"
      ],
      "sourceUrl": "https://defillama.com/protocol/everything",
      "observedAt": "2026-07-12T16:52:28.179Z"
    },
    {
      "id": "protocol:4223",
      "kind": "protocol",
      "name": "Ring Few",
      "type": "defi",
      "chain": "Ethereum",
      "score": 61,
      "risk": {
        "level": "medium",
        "reasons": [
          "存在需要进一步核验的风险信号"
        ]
      },
      "summary": "Ring Few is a growing DeFi protocol with verifiable TVL and yield evidence.",
      "evidence": [
        "$30,440,422.99 TVL",
        "7.28% TVL change over 7 days"
      ],
      "sourceUrl": "https://defillama.com/protocol/ring-few",
      "observedAt": "2026-07-12T16:52:28.179Z"
    },
    {
      "id": "protocol:4922",
      "kind": "protocol",
      "name": "PumpBTC",
      "type": "defi",
      "chain": "BNB Chain",
      "score": 61,
      "risk": {
        "level": "medium",
        "reasons": [
          "存在需要进一步核验的风险信号"
        ]
      },
      "summary": "PumpBTC is a growing DeFi protocol with verifiable TVL and yield evidence.",
      "evidence": [
        "$47,817,098.23 TVL",
        "2.06% TVL change over 7 days"
      ],
      "sourceUrl": "https://defillama.com/protocol/pumpbtc",
      "observedAt": "2026-07-12T16:52:28.179Z"
    },
    {
      "id": "protocol:641",
      "kind": "protocol",
      "name": "Arrakis V1",
      "type": "defi",
      "chain": "Ethereum",
      "score": 61,
      "risk": {
        "level": "medium",
        "reasons": [
          "存在需要进一步核验的风险信号"
        ]
      },
      "summary": "Arrakis V1 is a growing DeFi protocol with verifiable TVL and yield evidence.",
      "evidence": [
        "$1,372,758.16 TVL",
        "0.9% TVL change over 7 days"
      ],
      "sourceUrl": "https://defillama.com/protocol/arrakis-v1",
      "observedAt": "2026-07-12T16:52:28.179Z"
    },
    {
      "id": "protocol:4602",
      "kind": "protocol",
      "name": "vfat.io",
      "type": "defi",
      "chain": "Ethereum",
      "score": 60,
      "risk": {
        "level": "medium",
        "reasons": [
          "存在需要进一步核验的风险信号"
        ]
      },
      "summary": "vfat.io is a growing DeFi protocol with verifiable TVL and yield evidence.",
      "evidence": [
        "$32,044,003.5 TVL",
        "5.57% TVL change over 7 days"
      ],
      "sourceUrl": "https://defillama.com/protocol/vfat.io",
      "observedAt": "2026-07-12T16:52:28.179Z"
    },
    {
      "id": "protocol:5143",
      "kind": "protocol",
      "name": "Lombard Vaults",
      "type": "defi",
      "chain": "Ethereum",
      "score": 60,
      "risk": {
        "level": "medium",
        "reasons": [
          "存在需要进一步核验的风险信号"
        ]
      },
      "summary": "Lombard Vaults is a growing DeFi protocol with verifiable TVL and yield evidence.",
      "evidence": [
        "$37,816,906.11 TVL",
        "1.85% TVL change over 7 days"
      ],
      "sourceUrl": "https://defillama.com/protocol/lombard-vaults",
      "observedAt": "2026-07-12T16:52:28.179Z"
    },
    {
      "id": "protocol:6238",
      "kind": "protocol",
      "name": "SMARDEX USDN",
      "type": "defi",
      "chain": "Ethereum",
      "score": 60,
      "risk": {
        "level": "medium",
        "reasons": [
          "存在需要进一步核验的风险信号"
        ]
      },
      "summary": "SMARDEX USDN is a growing DeFi protocol with verifiable TVL and yield evidence.",
      "evidence": [
        "$1,152,109.04 TVL",
        "1.9% TVL change over 7 days"
      ],
      "sourceUrl": "https://defillama.com/protocol/smardex-usdn",
      "observedAt": "2026-07-12T16:52:28.179Z"
    },
    {
      "id": "protocol:7464",
      "kind": "protocol",
      "name": "Usual ETH0",
      "type": "defi",
      "chain": "Ethereum",
      "score": 60,
      "risk": {
        "level": "medium",
        "reasons": [
          "存在需要进一步核验的风险信号"
        ]
      },
      "summary": "Usual ETH0 is a growing DeFi protocol with verifiable TVL and yield evidence.",
      "evidence": [
        "$1,649,137.86 TVL",
        "2.41% TVL change over 7 days"
      ],
      "sourceUrl": "https://defillama.com/protocol/usual-eth0",
      "observedAt": "2026-07-12T16:52:28.179Z"
    },
    {
      "id": "protocol:7254",
      "kind": "protocol",
      "name": "Lazy",
      "type": "defi",
      "chain": "Ethereum",
      "score": 59,
      "risk": {
        "level": "medium",
        "reasons": [
          "存在需要进一步核验的风险信号"
        ]
      },
      "summary": "Lazy is a growing DeFi protocol with verifiable TVL and yield evidence.",
      "evidence": [
        "$1,026,047.3 TVL",
        "0.2% TVL change over 7 days"
      ],
      "sourceUrl": "https://defillama.com/protocol/lazy",
      "observedAt": "2026-07-12T16:52:28.179Z"
    },
    {
      "id": "protocol:2231",
      "kind": "protocol",
      "name": "Tangible RWA",
      "type": "defi",
      "chain": "Ethereum",
      "score": 58,
      "risk": {
        "level": "medium",
        "reasons": [
          "存在需要进一步核验的风险信号"
        ]
      },
      "summary": "Tangible RWA is a growing DeFi protocol with verifiable TVL and yield evidence.",
      "evidence": [
        "$41,993,977.05 TVL",
        "0.35% TVL change over 7 days"
      ],
      "sourceUrl": "https://defillama.com/protocol/tangible-rwa",
      "observedAt": "2026-07-12T16:52:28.179Z"
    },
    {
      "id": "protocol:3208",
      "kind": "protocol",
      "name": "UNCX Network V3",
      "type": "defi",
      "chain": "Ethereum",
      "score": 58,
      "risk": {
        "level": "medium",
        "reasons": [
          "存在需要进一步核验的风险信号"
        ]
      },
      "summary": "UNCX Network V3 is a growing DeFi protocol with verifiable TVL and yield evidence.",
      "evidence": [
        "$21,845,407.4 TVL",
        "0.74% TVL change over 7 days"
      ],
      "sourceUrl": "https://defillama.com/protocol/uncx-network-v3",
      "observedAt": "2026-07-12T16:52:28.179Z"
    },
    {
      "id": "protocol:4236",
      "kind": "protocol",
      "name": "Blast Bridge",
      "type": "defi",
      "chain": "Ethereum",
      "score": 58,
      "risk": {
        "level": "medium",
        "reasons": [
          "存在需要进一步核验的风险信号"
        ]
      },
      "summary": "Blast Bridge is a growing DeFi protocol with verifiable TVL and yield evidence.",
      "evidence": [
        "$49,748,126.91 TVL",
        "1.04% TVL change over 7 days"
      ],
      "sourceUrl": "https://defillama.com/protocol/blast-bridge",
      "observedAt": "2026-07-12T16:52:28.179Z"
    },
    {
      "id": "protocol:4238",
      "kind": "protocol",
      "name": "Zircuit Staking",
      "type": "defi",
      "chain": "Ethereum",
      "score": 58,
      "risk": {
        "level": "medium",
        "reasons": [
          "存在需要进一步核验的风险信号"
        ]
      },
      "summary": "Zircuit Staking is a growing DeFi protocol with verifiable TVL and yield evidence.",
      "evidence": [
        "$43,743,742.15 TVL",
        "1.96% TVL change over 7 days"
      ],
      "sourceUrl": "https://defillama.com/protocol/zircuit-staking",
      "observedAt": "2026-07-12T16:52:28.179Z"
    },
    {
      "id": "protocol:4323",
      "kind": "protocol",
      "name": "Aera V2",
      "type": "defi",
      "chain": "Ethereum",
      "score": 58,
      "risk": {
        "level": "medium",
        "reasons": [
          "存在需要进一步核验的风险信号"
        ]
      },
      "summary": "Aera V2 is a growing DeFi protocol with verifiable TVL and yield evidence.",
      "evidence": [
        "$38,423,326.61 TVL",
        "4.06% TVL change over 7 days"
      ],
      "sourceUrl": "https://defillama.com/protocol/aera-v2",
      "observedAt": "2026-07-12T16:52:28.179Z"
    },
    {
      "id": "protocol:4756",
      "kind": "protocol",
      "name": "Mellow Restaking",
      "type": "defi",
      "chain": "Ethereum",
      "score": 58,
      "risk": {
        "level": "medium",
        "reasons": [
          "存在需要进一步核验的风险信号"
        ]
      },
      "summary": "Mellow Restaking is a growing DeFi protocol with verifiable TVL and yield evidence.",
      "evidence": [
        "$20,935,748.84 TVL",
        "2.78% TVL change over 7 days"
      ],
      "sourceUrl": "https://defillama.com/protocol/mellow-restaking",
      "observedAt": "2026-07-12T16:52:28.179Z"
    },
    {
      "id": "protocol:5487",
      "kind": "protocol",
      "name": "Nucleus",
      "type": "defi",
      "chain": "Ethereum",
      "score": 58,
      "risk": {
        "level": "medium",
        "reasons": [
          "存在需要进一步核验的风险信号"
        ]
      },
      "summary": "Nucleus is a growing DeFi protocol with verifiable TVL and yield evidence.",
      "evidence": [
        "$25,502,969.01 TVL",
        "7.15% TVL change over 7 days"
      ],
      "sourceUrl": "https://defillama.com/protocol/nucleus",
      "observedAt": "2026-07-12T16:52:28.179Z"
    },
    {
      "id": "protocol:6203",
      "kind": "protocol",
      "name": "Hakutora",
      "type": "defi",
      "chain": "Ethereum",
      "score": 58,
      "risk": {
        "level": "medium",
        "reasons": [
          "存在需要进一步核验的风险信号"
        ]
      },
      "summary": "Hakutora is a growing DeFi protocol with verifiable TVL and yield evidence.",
      "evidence": [
        "$25,318,611.62 TVL",
        "5.13% TVL change over 7 days"
      ],
      "sourceUrl": "https://defillama.com/protocol/hakutora",
      "observedAt": "2026-07-12T16:52:28.179Z"
    },
    {
      "id": "protocol:6763",
      "kind": "protocol",
      "name": "SunX Bridge",
      "type": "defi",
      "chain": "Ethereum",
      "score": 58,
      "risk": {
        "level": "medium",
        "reasons": [
          "存在需要进一步核验的风险信号"
        ]
      },
      "summary": "SunX Bridge is a growing DeFi protocol with verifiable TVL and yield evidence.",
      "evidence": [
        "$25,534,746.58 TVL",
        "1.47% TVL change over 7 days"
      ],
      "sourceUrl": "https://defillama.com/protocol/sunx-bridge",
      "observedAt": "2026-07-12T16:52:28.179Z"
    },
    {
      "id": "protocol:7750",
      "kind": "protocol",
      "name": "Flying Tulip Lend",
      "type": "defi",
      "chain": "Ethereum",
      "score": 58,
      "risk": {
        "level": "medium",
        "reasons": [
          "存在需要进一步核验的风险信号"
        ]
      },
      "summary": "Flying Tulip Lend is a growing DeFi protocol with verifiable TVL and yield evidence.",
      "evidence": [
        "$9,366,970.16 TVL",
        "18.68% TVL change over 7 days"
      ],
      "sourceUrl": "https://defillama.com/protocol/flying-tulip-lend",
      "observedAt": "2026-07-12T16:52:28.179Z"
    },
    {
      "id": "protocol:144",
      "kind": "protocol",
      "name": "dYdX V3",
      "type": "defi",
      "chain": "Ethereum",
      "score": 57,
      "risk": {
        "level": "medium",
        "reasons": [
          "存在需要进一步核验的风险信号"
        ]
      },
      "summary": "dYdX V3 is a growing DeFi protocol with verifiable TVL and yield evidence.",
      "evidence": [
        "$37,714,063.9 TVL",
        "0.18% TVL change over 7 days"
      ],
      "sourceUrl": "https://defillama.com/protocol/dydx-v3",
      "observedAt": "2026-07-12T16:52:28.179Z"
    },
    {
      "id": "protocol:3091",
      "kind": "protocol",
      "name": "Equilibria",
      "type": "defi",
      "chain": "Ethereum",
      "score": 57,
      "risk": {
        "level": "medium",
        "reasons": [
          "存在需要进一步核验的风险信号"
        ]
      },
      "summary": "Equilibria is a growing DeFi protocol with verifiable TVL and yield evidence.",
      "evidence": [
        "$11,043,867.04 TVL",
        "6.22% TVL change over 7 days"
      ],
      "sourceUrl": "https://defillama.com/protocol/equilibria",
      "observedAt": "2026-07-12T16:52:28.179Z"
    },
    {
      "id": "protocol:3783",
      "kind": "protocol",
      "name": "Metis Bridge",
      "type": "defi",
      "chain": "Ethereum",
      "score": 57,
      "risk": {
        "level": "medium",
        "reasons": [
          "存在需要进一步核验的风险信号"
        ]
      },
      "summary": "Metis Bridge is a growing DeFi protocol with verifiable TVL and yield evidence.",
      "evidence": [
        "$26,131,901.21 TVL",
        "1.93% TVL change over 7 days"
      ],
      "sourceUrl": "https://defillama.com/protocol/metis-bridge",
      "observedAt": "2026-07-12T16:52:28.179Z"
    },
    {
      "id": "protocol:5351",
      "kind": "protocol",
      "name": "Mantle Restaking",
      "type": "defi",
      "chain": "Ethereum",
      "score": 57,
      "risk": {
        "level": "medium",
        "reasons": [
          "存在需要进一步核验的风险信号"
        ]
      },
      "summary": "Mantle Restaking is a growing DeFi protocol with verifiable TVL and yield evidence.",
      "evidence": [
        "$34,670,696.93 TVL",
        "1.12% TVL change over 7 days"
      ],
      "sourceUrl": "https://defillama.com/protocol/mantle-restaking",
      "observedAt": "2026-07-12T16:52:28.179Z"
    },
    {
      "id": "protocol:5397",
      "kind": "protocol",
      "name": "Bitlayer YBTC Family",
      "type": "defi",
      "chain": "Ethereum",
      "score": 57,
      "risk": {
        "level": "medium",
        "reasons": [
          "存在需要进一步核验的风险信号"
        ]
      },
      "summary": "Bitlayer YBTC Family is a growing DeFi protocol with verifiable TVL and yield evidence.",
      "evidence": [
        "$25,811,970.12 TVL",
        "2.29% TVL change over 7 days"
      ],
      "sourceUrl": "https://defillama.com/protocol/bitlayer-ybtc-family",
      "observedAt": "2026-07-12T16:52:28.179Z"
    },
    {
      "id": "protocol:5548",
      "kind": "protocol",
      "name": "Neutral Trade",
      "type": "defi",
      "chain": "Solana",
      "score": 57,
      "risk": {
        "level": "medium",
        "reasons": [
          "存在需要进一步核验的风险信号"
        ]
      },
      "summary": "Neutral Trade is a growing DeFi protocol with verifiable TVL and yield evidence.",
      "evidence": [
        "$13,145,586.29 TVL",
        "10.55% TVL change over 7 days"
      ],
      "sourceUrl": "https://defillama.com/protocol/neutral-trade",
      "observedAt": "2026-07-12T16:52:28.179Z"
    },
    {
      "id": "protocol:5899",
      "kind": "protocol",
      "name": "Bitbond Lockers",
      "type": "defi",
      "chain": "BNB Chain",
      "score": 57,
      "risk": {
        "level": "medium",
        "reasons": [
          "存在需要进一步核验的风险信号"
        ]
      },
      "summary": "Bitbond Lockers is a growing DeFi protocol with verifiable TVL and yield evidence.",
      "evidence": [
        "$9,716,852.86 TVL",
        "8.17% TVL change over 7 days"
      ],
      "sourceUrl": "https://defillama.com/protocol/bitbond-lockers",
      "observedAt": "2026-07-12T16:52:28.179Z"
    },
    {
      "id": "protocol:7749",
      "kind": "protocol",
      "name": "Alchemix V3",
      "type": "defi",
      "chain": "Ethereum",
      "score": 57,
      "risk": {
        "level": "medium",
        "reasons": [
          "存在需要进一步核验的风险信号"
        ]
      },
      "summary": "Alchemix V3 is a growing DeFi protocol with verifiable TVL and yield evidence.",
      "evidence": [
        "$31,520,965.38 TVL",
        "1.48% TVL change over 7 days"
      ],
      "sourceUrl": "https://defillama.com/protocol/alchemix-v3",
      "observedAt": "2026-07-12T16:52:28.179Z"
    },
    {
      "id": "protocol:2807",
      "kind": "protocol",
      "name": "MatrixDock STBT",
      "type": "defi",
      "chain": "Ethereum",
      "score": 56,
      "risk": {
        "level": "medium",
        "reasons": [
          "存在需要进一步核验的风险信号"
        ]
      },
      "summary": "MatrixDock STBT is a growing DeFi protocol with verifiable TVL and yield evidence.",
      "evidence": [
        "$23,555,626.66 TVL",
        "0.93% TVL change over 7 days"
      ],
      "sourceUrl": "https://defillama.com/protocol/matrixdock-stbt",
      "observedAt": "2026-07-12T16:52:28.179Z"
    },
    {
      "id": "protocol:3043",
      "kind": "protocol",
      "name": "Steer Protocol",
      "type": "defi",
      "chain": "BNB Chain",
      "score": 56,
      "risk": {
        "level": "medium",
        "reasons": [
          "存在需要进一步核验的风险信号"
        ]
      },
      "summary": "Steer Protocol is a growing DeFi protocol with verifiable TVL and yield evidence.",
      "evidence": [
        "$16,303,367.59 TVL",
        "0.01% TVL change over 7 days"
      ],
      "sourceUrl": "https://defillama.com/protocol/steer-protocol",
      "observedAt": "2026-07-12T16:52:28.179Z"
    },
    {
      "id": "protocol:3948",
      "kind": "protocol",
      "name": "Chain Fusion",
      "type": "defi",
      "chain": "Ethereum",
      "score": 56,
      "risk": {
        "level": "medium",
        "reasons": [
          "存在需要进一步核验的风险信号"
        ]
      },
      "summary": "Chain Fusion is a growing DeFi protocol with verifiable TVL and yield evidence.",
      "evidence": [
        "$19,683,989.21 TVL",
        "4.97% TVL change over 7 days"
      ],
      "sourceUrl": "https://defillama.com/protocol/chain-fusion",
      "observedAt": "2026-07-12T16:52:28.179Z"
    },
    {
      "id": "protocol:4032",
      "kind": "protocol",
      "name": "Manta Pacific",
      "type": "defi",
      "chain": "Ethereum",
      "score": 56,
      "risk": {
        "level": "medium",
        "reasons": [
          "存在需要进一步核验的风险信号"
        ]
      },
      "summary": "Manta Pacific is a growing DeFi protocol with verifiable TVL and yield evidence.",
      "evidence": [
        "$22,483,351.68 TVL",
        "2.42% TVL change over 7 days"
      ],
      "sourceUrl": "https://defillama.com/protocol/manta-pacific",
      "observedAt": "2026-07-12T16:52:28.179Z"
    },
    {
      "id": "protocol:5513",
      "kind": "protocol",
      "name": "Ink Bridge",
      "type": "defi",
      "chain": "Ethereum",
      "score": 56,
      "risk": {
        "level": "medium",
        "reasons": [
          "存在需要进一步核验的风险信号"
        ]
      },
      "summary": "Ink Bridge is a growing DeFi protocol with verifiable TVL and yield evidence.",
      "evidence": [
        "$22,425,433.67 TVL",
        "3.33% TVL change over 7 days"
      ],
      "sourceUrl": "https://defillama.com/protocol/ink-bridge",
      "observedAt": "2026-07-12T16:52:28.179Z"
    },
    {
      "id": "protocol:5691",
      "kind": "protocol",
      "name": "Abstract",
      "type": "defi",
      "chain": "Ethereum",
      "score": 56,
      "risk": {
        "level": "medium",
        "reasons": [
          "存在需要进一步核验的风险信号"
        ]
      },
      "summary": "Abstract is a growing DeFi protocol with verifiable TVL and yield evidence.",
      "evidence": [
        "$25,854,386.31 TVL",
        "0.25% TVL change over 7 days"
      ],
      "sourceUrl": "https://defillama.com/protocol/abstract",
      "observedAt": "2026-07-12T16:52:28.179Z"
    },
    {
      "id": "protocol:5695",
      "kind": "protocol",
      "name": "Gravity by Galxe",
      "type": "defi",
      "chain": "Ethereum",
      "score": 56,
      "risk": {
        "level": "medium",
        "reasons": [
          "存在需要进一步核验的风险信号"
        ]
      },
      "summary": "Gravity by Galxe is a growing DeFi protocol with verifiable TVL and yield evidence.",
      "evidence": [
        "$20,998,232.94 TVL",
        "2.84% TVL change over 7 days"
      ],
      "sourceUrl": "https://defillama.com/protocol/gravity-by-galxe",
      "observedAt": "2026-07-12T16:52:28.179Z"
    },
    {
      "id": "protocol:5946",
      "kind": "protocol",
      "name": "TermFinance Vaults",
      "type": "defi",
      "chain": "Ethereum",
      "score": 56,
      "risk": {
        "level": "medium",
        "reasons": [
          "存在需要进一步核验的风险信号"
        ]
      },
      "summary": "TermFinance Vaults is a growing DeFi protocol with verifiable TVL and yield evidence.",
      "evidence": [
        "$11,905,334.23 TVL",
        "2.99% TVL change over 7 days"
      ],
      "sourceUrl": "https://defillama.com/protocol/termfinance-vaults",
      "observedAt": "2026-07-12T16:52:28.179Z"
    },
    {
      "id": "protocol:6682",
      "kind": "protocol",
      "name": "Pacifica Perps",
      "type": "defi",
      "chain": "Solana",
      "score": 56,
      "risk": {
        "level": "medium",
        "reasons": [
          "存在需要进一步核验的风险信号"
        ]
      },
      "summary": "Pacifica Perps is a growing DeFi protocol with verifiable TVL and yield evidence.",
      "evidence": [
        "$27,139,828.07 TVL",
        "0.28% TVL change over 7 days"
      ],
      "sourceUrl": "https://defillama.com/protocol/pacifica-perps",
      "observedAt": "2026-07-12T16:52:28.179Z"
    },
    {
      "id": "protocol:6963",
      "kind": "protocol",
      "name": "RockSolid Network",
      "type": "defi",
      "chain": "Ethereum",
      "score": 56,
      "risk": {
        "level": "medium",
        "reasons": [
          "存在需要进一步核验的风险信号"
        ]
      },
      "summary": "RockSolid Network is a growing DeFi protocol with verifiable TVL and yield evidence.",
      "evidence": [
        "$21,561,614.64 TVL",
        "3.04% TVL change over 7 days"
      ],
      "sourceUrl": "https://defillama.com/protocol/rocksolid-network",
      "observedAt": "2026-07-12T16:52:28.179Z"
    },
    {
      "id": "protocol:7388",
      "kind": "protocol",
      "name": "Twyne",
      "type": "defi",
      "chain": "Ethereum",
      "score": 56,
      "risk": {
        "level": "medium",
        "reasons": [
          "存在需要进一步核验的风险信号"
        ]
      },
      "summary": "Twyne is a growing DeFi protocol with verifiable TVL and yield evidence.",
      "evidence": [
        "$2,879,851.39 TVL",
        "25.73% TVL change over 7 days"
      ],
      "sourceUrl": "https://defillama.com/protocol/twyne",
      "observedAt": "2026-07-12T16:52:28.179Z"
    },
    {
      "id": "protocol:7421",
      "kind": "protocol",
      "name": "Avalon Superearn",
      "type": "defi",
      "chain": "Ethereum",
      "score": 56,
      "risk": {
        "level": "medium",
        "reasons": [
          "存在需要进一步核验的风险信号"
        ]
      },
      "summary": "Avalon Superearn is a growing DeFi protocol with verifiable TVL and yield evidence.",
      "evidence": [
        "$30,599,761.02 TVL",
        "0.09% TVL change over 7 days"
      ],
      "sourceUrl": "https://defillama.com/protocol/avalon-superearn",
      "observedAt": "2026-07-12T16:52:28.179Z"
    },
    {
      "id": "protocol:801",
      "kind": "protocol",
      "name": "cBridge",
      "type": "defi",
      "chain": "Ethereum",
      "score": 56,
      "risk": {
        "level": "medium",
        "reasons": [
          "存在需要进一步核验的风险信号"
        ]
      },
      "summary": "cBridge is a growing DeFi protocol with verifiable TVL and yield evidence.",
      "evidence": [
        "$13,524,180.17 TVL",
        "1.56% TVL change over 7 days"
      ],
      "sourceUrl": "https://defillama.com/protocol/cbridge",
      "observedAt": "2026-07-12T16:52:28.179Z"
    },
    {
      "id": "protocol:1571",
      "kind": "protocol",
      "name": "Stargate V1",
      "type": "defi",
      "chain": "Ethereum",
      "score": 55,
      "risk": {
        "level": "medium",
        "reasons": [
          "存在需要进一步核验的风险信号"
        ]
      },
      "summary": "Stargate V1 is a growing DeFi protocol with verifiable TVL and yield evidence.",
      "evidence": [
        "$9,870,889.94 TVL",
        "1.74% TVL change over 7 days"
      ],
      "sourceUrl": "https://defillama.com/protocol/stargate-v1",
      "observedAt": "2026-07-12T16:52:28.179Z"
    },
    {
      "id": "protocol:172",
      "kind": "protocol",
      "name": "Index Coop",
      "type": "defi",
      "chain": "Ethereum",
      "score": 55,
      "risk": {
        "level": "medium",
        "reasons": [
          "存在需要进一步核验的风险信号"
        ]
      },
      "summary": "Index Coop is a growing DeFi protocol with verifiable TVL and yield evidence.",
      "evidence": [
        "$10,373,512.7 TVL",
        "5.89% TVL change over 7 days"
      ],
      "sourceUrl": "https://defillama.com/protocol/index-coop",
      "observedAt": "2026-07-12T16:52:28.179Z"
    },
    {
      "id": "protocol:190",
      "kind": "protocol",
      "name": "Chamber Vaults",
      "type": "defi",
      "chain": "Ethereum",
      "score": 55,
      "risk": {
        "level": "medium",
        "reasons": [
          "存在需要进一步核验的风险信号"
        ]
      },
      "summary": "Chamber Vaults is a growing DeFi protocol with verifiable TVL and yield evidence.",
      "evidence": [
        "$19,996,978.89 TVL",
        "1.07% TVL change over 7 days"
      ],
      "sourceUrl": "https://defillama.com/protocol/chamber-vaults",
      "observedAt": "2026-07-12T16:52:28.179Z"
    },
    {
      "id": "protocol:1995",
      "kind": "protocol",
      "name": "Bancor V3",
      "type": "defi",
      "chain": "Ethereum",
      "score": 55,
      "risk": {
        "level": "medium",
        "reasons": [
          "存在需要进一步核验的风险信号"
        ]
      },
      "summary": "Bancor V3 is a growing DeFi protocol with verifiable TVL and yield evidence.",
      "evidence": [
        "$17,063,308.37 TVL",
        "1.93% TVL change over 7 days"
      ],
      "sourceUrl": "https://defillama.com/protocol/bancor-v3",
      "observedAt": "2026-07-12T16:52:28.179Z"
    },
    {
      "id": "protocol:208",
      "kind": "protocol",
      "name": "ACryptoS",
      "type": "defi",
      "chain": "BNB Chain",
      "score": 55,
      "risk": {
        "level": "medium",
        "reasons": [
          "存在需要进一步核验的风险信号"
        ]
      },
      "summary": "ACryptoS is a growing DeFi protocol with verifiable TVL and yield evidence.",
      "evidence": [
        "$10,557,983 TVL",
        "0.03% TVL change over 7 days"
      ],
      "sourceUrl": "https://defillama.com/protocol/acryptos",
      "observedAt": "2026-07-12T16:52:28.179Z"
    },
    {
      "id": "protocol:2121",
      "kind": "protocol",
      "name": "Frax Swap",
      "type": "defi",
      "chain": "Ethereum",
      "score": 55,
      "risk": {
        "level": "medium",
        "reasons": [
          "存在需要进一步核验的风险信号"
        ]
      },
      "summary": "Frax Swap is a growing DeFi protocol with verifiable TVL and yield evidence.",
      "evidence": [
        "$9,567,487.88 TVL",
        "1.48% TVL change over 7 days"
      ],
      "sourceUrl": "https://defillama.com/protocol/frax-swap",
      "observedAt": "2026-07-12T16:52:28.179Z"
    },
    {
      "id": "protocol:3558",
      "kind": "protocol",
      "name": "StakeStone STONE",
      "type": "defi",
      "chain": "Ethereum",
      "score": 55,
      "risk": {
        "level": "medium",
        "reasons": [
          "存在需要进一步核验的风险信号"
        ]
      },
      "summary": "StakeStone STONE is a growing DeFi protocol with verifiable TVL and yield evidence.",
      "evidence": [
        "$17,029,430.44 TVL",
        "2.23% TVL change over 7 days"
      ],
      "sourceUrl": "https://defillama.com/protocol/stakestone-stone",
      "observedAt": "2026-07-12T16:52:28.179Z"
    },
    {
      "id": "protocol:3791",
      "kind": "protocol",
      "name": "Maya Protocol",
      "type": "defi",
      "chain": "Ethereum",
      "score": 55,
      "risk": {
        "level": "medium",
        "reasons": [
          "存在需要进一步核验的风险信号"
        ]
      },
      "summary": "Maya Protocol is a growing DeFi protocol with verifiable TVL and yield evidence.",
      "evidence": [
        "$11,519,659.97 TVL",
        "5.84% TVL change over 7 days"
      ],
      "sourceUrl": "https://defillama.com/protocol/maya-protocol",
      "observedAt": "2026-07-12T16:52:28.179Z"
    },
    {
      "id": "protocol:4158",
      "kind": "protocol",
      "name": "Crypto.com Liquid Staking",
      "type": "defi",
      "chain": "Solana",
      "score": 55,
      "risk": {
        "level": "medium",
        "reasons": [
          "存在需要进一步核验的风险信号"
        ]
      },
      "summary": "Crypto.com Liquid Staking is a growing DeFi protocol with verifiable TVL and yield evidence.",
      "evidence": [
        "$21,868,613.46 TVL",
        "0.3% TVL change over 7 days"
      ],
      "sourceUrl": "https://defillama.com/protocol/crypto.com-liquid-staking",
      "observedAt": "2026-07-12T16:52:28.179Z"
    },
    {
      "id": "protocol:4879",
      "kind": "protocol",
      "name": "Clearpool TPOOL",
      "type": "defi",
      "chain": "Ethereum",
      "score": 55,
      "risk": {
        "level": "medium",
        "reasons": [
          "存在需要进一步核验的风险信号"
        ]
      },
      "summary": "Clearpool TPOOL is a growing DeFi protocol with verifiable TVL and yield evidence.",
      "evidence": [
        "$21,322,062.26 TVL",
        "0.03% TVL change over 7 days"
      ],
      "sourceUrl": "https://defillama.com/protocol/clearpool-tpool",
      "observedAt": "2026-07-12T16:52:28.179Z"
    },
    {
      "id": "protocol:5001",
      "kind": "protocol",
      "name": "Capyfi",
      "type": "defi",
      "chain": "Ethereum",
      "score": 55,
      "risk": {
        "level": "medium",
        "reasons": [
          "存在需要进一步核验的风险信号"
        ]
      },
      "summary": "Capyfi is a growing DeFi protocol with verifiable TVL and yield evidence.",
      "evidence": [
        "$10,402,978.37 TVL",
        "7.18% TVL change over 7 days"
      ],
      "sourceUrl": "https://defillama.com/protocol/capyfi",
      "observedAt": "2026-07-12T16:52:28.179Z"
    },
    {
      "id": "protocol:5337",
      "kind": "protocol",
      "name": "Royco V1",
      "type": "defi",
      "chain": "Ethereum",
      "score": 55,
      "risk": {
        "level": "medium",
        "reasons": [
          "存在需要进一步核验的风险信号"
        ]
      },
      "summary": "Royco V1 is a growing DeFi protocol with verifiable TVL and yield evidence.",
      "evidence": [
        "$17,268,382.9 TVL",
        "1.91% TVL change over 7 days"
      ],
      "sourceUrl": "https://defillama.com/protocol/royco-v1",
      "observedAt": "2026-07-12T16:52:28.179Z"
    },
    {
      "id": "protocol:5338",
      "kind": "protocol",
      "name": "Hubra Staked SOL",
      "type": "defi",
      "chain": "Solana",
      "score": 55,
      "risk": {
        "level": "medium",
        "reasons": [
          "存在需要进一步核验的风险信号"
        ]
      },
      "summary": "Hubra Staked SOL is a growing DeFi protocol with verifiable TVL and yield evidence.",
      "evidence": [
        "$12,395,623.62 TVL",
        "4.8% TVL change over 7 days"
      ],
      "sourceUrl": "https://defillama.com/protocol/hubra-staked-sol",
      "observedAt": "2026-07-12T16:52:28.179Z"
    },
    {
      "id": "protocol:5349",
      "kind": "protocol",
      "name": "Manifest Trade",
      "type": "defi",
      "chain": "Solana",
      "score": 55,
      "risk": {
        "level": "medium",
        "reasons": [
          "存在需要进一步核验的风险信号"
        ]
      },
      "summary": "Manifest Trade is a growing DeFi protocol with verifiable TVL and yield evidence.",
      "evidence": [
        "$15,526,500.4 TVL",
        "3.91% TVL change over 7 days"
      ],
      "sourceUrl": "https://defillama.com/protocol/manifest-trade",
      "observedAt": "2026-07-12T16:52:28.179Z"
    },
    {
      "id": "protocol:6978",
      "kind": "protocol",
      "name": "BounceBit Prime",
      "type": "defi",
      "chain": "BNB Chain",
      "score": 55,
      "risk": {
        "level": "medium",
        "reasons": [
          "存在需要进一步核验的风险信号"
        ]
      },
      "summary": "BounceBit Prime is a growing DeFi protocol with verifiable TVL and yield evidence.",
      "evidence": [
        "$11,449,172.56 TVL",
        "0.02% TVL change over 7 days"
      ],
      "sourceUrl": "https://defillama.com/protocol/bouncebit-prime",
      "observedAt": "2026-07-12T16:52:28.179Z"
    },
    {
      "id": "protocol:4866",
      "kind": "protocol",
      "name": "VNX",
      "type": "defi",
      "chain": "Solana",
      "score": 54,
      "risk": {
        "level": "medium",
        "reasons": [
          "存在需要进一步核验的风险信号"
        ]
      },
      "summary": "VNX is a growing DeFi protocol with verifiable TVL and yield evidence.",
      "evidence": [
        "$5,494,814.43 TVL",
        "5.52% TVL change over 7 days"
      ],
      "sourceUrl": "https://defillama.com/protocol/vnx",
      "observedAt": "2026-07-12T16:52:28.179Z"
    },
    {
      "id": "protocol:6291",
      "kind": "protocol",
      "name": "The Vault Unstake Pool",
      "type": "defi",
      "chain": "Solana",
      "score": 54,
      "risk": {
        "level": "medium",
        "reasons": [
          "存在需要进一步核验的风险信号"
        ]
      },
      "summary": "The Vault Unstake Pool is a growing DeFi protocol with verifiable TVL and yield evidence.",
      "evidence": [
        "$1,081,130.15 TVL",
        "27.31% TVL change over 7 days"
      ],
      "sourceUrl": "https://defillama.com/protocol/the-vault-unstake-pool",
      "observedAt": "2026-07-12T16:52:28.179Z"
    },
    {
      "id": "protocol:6368",
      "kind": "protocol",
      "name": "Byreal",
      "type": "defi",
      "chain": "Solana",
      "score": 54,
      "risk": {
        "level": "medium",
        "reasons": [
          "存在需要进一步核验的风险信号"
        ]
      },
      "summary": "Byreal is a growing DeFi protocol with verifiable TVL and yield evidence.",
      "evidence": [
        "$12,653,116.31 TVL",
        "2.21% TVL change over 7 days"
      ],
      "sourceUrl": "https://defillama.com/protocol/byreal",
      "observedAt": "2026-07-12T16:52:28.179Z"
    },
    {
      "id": "protocol:7204",
      "kind": "protocol",
      "name": "Perena Vaults",
      "type": "defi",
      "chain": "Solana",
      "score": 54,
      "risk": {
        "level": "medium",
        "reasons": [
          "存在需要进一步核验的风险信号"
        ]
      },
      "summary": "Perena Vaults is a growing DeFi protocol with verifiable TVL and yield evidence.",
      "evidence": [
        "$7,731,662.61 TVL",
        "7.7% TVL change over 7 days"
      ],
      "sourceUrl": "https://defillama.com/protocol/perena-vaults",
      "observedAt": "2026-07-12T16:52:28.179Z"
    },
    {
      "id": "protocol:310",
      "kind": "protocol",
      "name": "Belt Finance",
      "type": "defi",
      "chain": "BNB Chain",
      "score": 53,
      "risk": {
        "level": "medium",
        "reasons": [
          "存在需要进一步核验的风险信号"
        ]
      },
      "summary": "Belt Finance is a growing DeFi protocol with verifiable TVL and yield evidence.",
      "evidence": [
        "$11,268,765.91 TVL",
        "0.4% TVL change over 7 days"
      ],
      "sourceUrl": "https://defillama.com/protocol/belt-finance",
      "observedAt": "2026-07-12T16:52:28.179Z"
    },
    {
      "id": "protocol:7418",
      "kind": "protocol",
      "name": "Paimon",
      "type": "defi",
      "chain": "BNB Chain",
      "score": 53,
      "risk": {
        "level": "medium",
        "reasons": [
          "存在需要进一步核验的风险信号"
        ]
      },
      "summary": "Paimon is a growing DeFi protocol with verifiable TVL and yield evidence.",
      "evidence": [
        "$11,780,988.46 TVL",
        "0.14% TVL change over 7 days"
      ],
      "sourceUrl": "https://defillama.com/protocol/paimon",
      "observedAt": "2026-07-12T16:52:28.179Z"
    },
    {
      "id": "protocol:183",
      "kind": "protocol",
      "name": "Wing Finance",
      "type": "defi",
      "chain": "BNB Chain",
      "score": 52,
      "risk": {
        "level": "medium",
        "reasons": [
          "存在需要进一步核验的风险信号"
        ]
      },
      "summary": "Wing Finance is a growing DeFi protocol with verifiable TVL and yield evidence.",
      "evidence": [
        "$4,783,193.72 TVL",
        "1.1% TVL change over 7 days"
      ],
      "sourceUrl": "https://defillama.com/protocol/wing-finance",
      "observedAt": "2026-07-12T16:52:28.179Z"
    },
    {
      "id": "protocol:2254",
      "kind": "protocol",
      "name": "MUX Perps",
      "type": "defi",
      "chain": "BNB Chain",
      "score": 52,
      "risk": {
        "level": "medium",
        "reasons": [
          "存在需要进一步核验的风险信号"
        ]
      },
      "summary": "MUX Perps is a growing DeFi protocol with verifiable TVL and yield evidence.",
      "evidence": [
        "$8,606,363.63 TVL",
        "1.51% TVL change over 7 days"
      ],
      "sourceUrl": "https://defillama.com/protocol/mux-perps",
      "observedAt": "2026-07-12T16:52:28.179Z"
    },
    {
      "id": "protocol:3573",
      "kind": "protocol",
      "name": "Solv RWA",
      "type": "defi",
      "chain": "BNB Chain",
      "score": 52,
      "risk": {
        "level": "medium",
        "reasons": [
          "存在需要进一步核验的风险信号"
        ]
      },
      "summary": "Solv RWA is a growing DeFi protocol with verifiable TVL and yield evidence.",
      "evidence": [
        "$7,500,975.09 TVL",
        "1.66% TVL change over 7 days"
      ],
      "sourceUrl": "https://defillama.com/protocol/solv-rwa",
      "observedAt": "2026-07-12T16:52:28.179Z"
    }
  ]
}
