{
  "generatedAt": "2026-07-11T02:00:33.819Z",
  "stale": false,
  "sourceStatus": {
    "dexscreener": {
      "status": "ok",
      "observedAt": "2026-07-11T02:00:33.819Z"
    },
    "defillama": {
      "status": "ok",
      "observedAt": "2026-07-11T02:00:33.819Z"
    },
    "rpc": {
      "status": "ok",
      "observedAt": "2026-07-11T02:00:33.819Z"
    }
  },
  "chainHeads": {
    "ethereum": {
      "height": 25506241,
      "observedAt": "2026-07-11T02:00:34.118Z",
      "status": "ok"
    },
    "bsc": {
      "height": 109279948,
      "observedAt": "2026-07-11T02:00:34.235Z",
      "status": "ok"
    },
    "solana": {
      "height": 432130160,
      "observedAt": "2026-07-11T02:00:34.242Z",
      "status": "ok"
    }
  },
  "rejected": {
    "pools": 20,
    "protocols": 2433,
    "yields": 6894
  }
}
